[{
  "_id": {
    "$oid": "656a815c9fbd268c204f0304"
  },
  "name": "Aachen",
  "year": 1880,
  "reclat": 50.775,
  "reclong": 6.08333
},
{
  "_id": {
    "$oid": "656a815c9fbd268c204f030b"
  },
  "name": "Agen",
  "year": 1814,
  "reclat": 44.21667,
  "reclong": 0.61667
},
{
  "_id": {
    "$oid": "656a815c9fbd268c204f0312"
  },
  "name": "Akbarpur",
  "year": 1838,
  "reclat": 29.71667,
  "reclong": 77.95
},
{
  "_id": {
    "$oid": "656a815c9fbd268c204f0317"
  },
  "name": "Alais",
  "year": 1806,
  "reclat": 44.11667,
  "reclong": 4.08333
},
{
  "_id": {
    "$oid": "656a815c9fbd268c204f031b"
  },
  "name": "Aldsworth",
  "year": 1835,
  "reclat": 51.78333,
  "reclong": -1.78333
},
{
  "_id": {
    "$oid": "656a815c9fbd268c204f031c"
  },
  "name": "Aleppo",
  "year": 1873,
  "reclat": 36.23333,
  "reclong": 37.13333
},
{
  "_id": {
    "$oid": "656a815c9fbd268c204f031d"
  },
  "name": "Alessandria",
  "year": 1860,
  "reclat": 44.88333,
  "reclong": 8.75
},
{
  "_id": {
    "$oid": "656a815c9fbd268c204f031e"
  },
  "name": "Alexandrovsky",
  "year": 1900,
  "reclat": 50.95,
  "reclong": 31.81667
},
{
  "_id": {
    "$oid": "656a815c9fbd268c204f031f"
  },
  "name": "Alfianello",
  "year": 1883,
  "reclat": 45.26667,
  "reclong": 10.15
},
{
  "_id": {
    "$oid": "656a815c9fbd268c204f0320"
  },
  "name": "Allegan",
  "year": 1899,
  "reclat": 42.53333,
  "reclong": -85.88333
},
{
  "_id": {
    "$oid": "656a815c9fbd268c204f0324"
  },
  "name": "Ambapur Nagla",
  "year": 1895,
  "reclat": 27.66667,
  "reclong": 78.25
},
{
  "_id": {
    "$oid": "656a815c9fbd268c204f0325"
  },
  "name": "Andhara",
  "year": 1880,
  "reclat": 26.58333,
  "reclong": 85.56667
},
{
  "_id": {
    "$oid": "656a815c9fbd268c204f0326"
  },
  "name": "Andover",
  "year": 1898,
  "reclat": 44.61667,
  "reclong": -70.75
},
{
  "_id": {
    "$oid": "656a815c9fbd268c204f032a"
  },
  "name": "Angers",
  "year": 1822,
  "reclat": 47.46667,
  "reclong": -0.55
},
{
  "_id": {
    "$oid": "656a815c9fbd268c204f032b"
  },
  "name": "Angra dos Reis (stone)",
  "year": 1869,
  "reclat": -22.96667,
  "reclong": -44.31667
},
{
  "_id": {
    "$oid": "656a815c9fbd268c204f0330"
  },
  "name": "Apt",
  "year": 1803,
  "reclat": 43.86667,
  "reclong": 5.38333
},
{
  "_id": {
    "$oid": "656a815c9fbd268c204f0334"
  },
  "name": "Asco",
  "year": 1805,
  "reclat": 42.45,
  "reclong": 9.03333
},
{
  "_id": {
    "$oid": "656a815c9fbd268c204f0337"
  },
  "name": "Assisi",
  "year": 1886,
  "reclat": 43.03333,
  "reclong": 12.55
},
{
  "_id": {
    "$oid": "656a815c9fbd268c204f0339"
  },
  "name": "Atemajac",
  "year": 1896,
  "reclat": 20.06667,
  "reclong": -103.66667
},
{
  "_id": {
    "$oid": "656a815c9fbd268c204f033c"
  },
  "name": "Aubres",
  "year": 1836,
  "reclat": 44.38333,
  "reclong": 5.16667
},
{
  "_id": {
    "$oid": "656a815c9fbd268c204f033d"
  },
  "name": "Aumale",
  "year": 1865,
  "reclat": 36.16667,
  "reclong": 3.66667
},
{
  "_id": {
    "$oid": "656a815c9fbd268c204f033e"
  },
  "name": "Aumieres",
  "year": 1842,
  "reclat": 44.33333,
  "reclong": 3.23333
},
{
  "_id": {
    "$oid": "656a815c9fbd268c204f033f"
  },
  "name": "Ausson",
  "year": 1858,
  "reclat": 43.08333,
  "reclong": 0.58333
},
{
  "_id": {
    "$oid": "656a815c9fbd268c204f0342"
  },
  "name": "Avilez",
  "year": 1855,
  "reclat": 25,
  "reclong": -103.5
},
{
  "_id": {
    "$oid": "656a815c9fbd268c204f0345"
  },
  "name": "Bachmut",
  "year": 1814,
  "reclat": 48.6,
  "reclong": 38
},
{
  "_id": {
    "$oid": "656a815c9fbd268c204f034b"
  },
  "name": "Bandong",
  "year": 1871,
  "reclat": -6.91667,
  "reclong": 107.6
},
{
  "_id": {
    "$oid": "656a815c9fbd268c204f034c"
  },
  "name": "Bansur",
  "year": 1892,
  "reclat": 27.7,
  "reclong": 76.33333
},
{
  "_id": {
    "$oid": "656a815c9fbd268c204f0351"
  },
  "name": "Barea",
  "year": 1842,
  "reclat": 42.38333,
  "reclong": -2.5
},
{
  "_id": {
    "$oid": "656a815c9fbd268c204f0353"
  },
  "name": "Barntrup",
  "year": 1886,
  "reclat": 52,
  "reclong": 9.1
},
{
  "_id": {
    "$oid": "656a815c9fbd268c204f0358"
  },
  "name": "Bath",
  "year": 1892,
  "reclat": 45.41667,
  "reclong": -98.31667
},
{
  "_id": {
    "$oid": "656a815c9fbd268c204f035e"
  },
  "name": "Beaver Creek",
  "year": 1893,
  "reclat": 51.16667,
  "reclong": -117.33333
},
{
  "_id": {
    "$oid": "656a815c9fbd268c204f036b"
  },
  "name": "Berlanguillas",
  "year": 1811,
  "reclat": 41.68333,
  "reclong": -3.8
},
{
  "_id": {
    "$oid": "656a815c9fbd268c204f036d"
  },
  "name": "Bethlehem",
  "year": 1859,
  "reclat": 42.53333,
  "reclong": -73.83333
},
{
  "_id": {
    "$oid": "656a815c9fbd268c204f036e"
  },
  "name": "Beuste",
  "year": 1859,
  "reclat": 43.21667,
  "reclong": -0.23333
},
{
  "_id": {
    "$oid": "656a815c9fbd268c204f0370"
  },
  "name": "Bhagur",
  "year": 1877,
  "reclat": 20.88333,
  "reclong": 74.83333
},
{
  "_id": {
    "$oid": "656a815c9fbd268c204f0372"
  },
  "name": "Bherai",
  "year": 1893,
  "reclat": 20.83333,
  "reclong": 71.46667
},
{
  "_id": {
    "$oid": "656a815c9fbd268c204f0375"
  },
  "name": "Bialystok",
  "year": 1827,
  "reclat": 53.1,
  "reclong": 23.2
},
{
  "_id": {
    "$oid": "656a815c9fbd268c204f0376"
  },
  "name": "Bielokrynitschie",
  "year": 1887,
  "reclat": 50.13333,
  "reclong": 27.16667
},
{
  "_id": {
    "$oid": "656a815c9fbd268c204f037a"
  },
  "name": "Bishopville",
  "year": 1843,
  "reclat": 34.16667,
  "reclong": -80.28333
},
{
  "_id": {
    "$oid": "656a815c9fbd268c204f037b"
  },
  "name": "Bishunpur",
  "year": 1895,
  "reclat": 25.38333,
  "reclong": 82.6
},
{
  "_id": {
    "$oid": "656a815c9fbd268c204f037d"
  },
  "name": "Bjurböle",
  "year": 1899,
  "reclat": 60.4,
  "reclong": 25.8
},
{
  "_id": {
    "$oid": "656a815c9fbd268c204f0381"
  },
  "name": "Blansko",
  "year": 1833,
  "reclat": 49.36667,
  "reclong": 16.63333
},
{
  "_id": {
    "$oid": "656a815c9fbd268c204f0384"
  },
  "name": "Bocas",
  "year": 1804,
  "reclat": 23,
  "reclong": -102
},
{
  "_id": {
    "$oid": "656a815c9fbd268c204f0387"
  },
  "name": "Borgo San Donino",
  "year": 1808,
  "reclat": 44.86667,
  "reclong": 10.05
},
{
  "_id": {
    "$oid": "656a815c9fbd268c204f0388"
  },
  "name": "Bori",
  "year": 1894,
  "reclat": 21.95,
  "reclong": 78.03333
},
{
  "_id": {
    "$oid": "656a815c9fbd268c204f038a"
  },
  "name": "Borkut",
  "year": 1852,
  "reclat": 48.15,
  "reclong": 24.28333
},
{
  "_id": {
    "$oid": "656a815c9fbd268c204f038b"
  },
  "name": "Borodino",
  "year": 1812,
  "reclat": 55.46667,
  "reclong": 35.86667
},
{
  "_id": {
    "$oid": "656a815c9fbd268c204f038c"
  },
  "name": "Botschetschki",
  "year": 1823,
  "reclat": 51.33333,
  "reclong": 33.88333
},
{
  "_id": {
    "$oid": "656a815c9fbd268c204f0390"
  },
  "name": "Bradford Woods",
  "year": 1886,
  "reclat": 40.5,
  "reclong": -80.08333
},
{
  "_id": {
    "$oid": "656a815c9fbd268c204f0391"
  },
  "name": "Braunau",
  "year": 1847,
  "reclat": 50.6,
  "reclong": 16.3
},
{
  "_id": {
    "$oid": "656a815c9fbd268c204f0393"
  },
  "name": "Bremervörde",
  "year": 1855,
  "reclat": 53.4,
  "reclong": 9.1
},
{
  "_id": {
    "$oid": "656a815c9fbd268c204f039d"
  },
  "name": "Buschhof",
  "year": 1863,
  "reclat": 46.45,
  "reclong": 25.78333
},
{
  "_id": {
    "$oid": "656a815c9fbd268c204f039e"
  },
  "name": "Bustee",
  "year": 1852,
  "reclat": 26.78333,
  "reclong": 82.83333
},
{
  "_id": {
    "$oid": "656a815c9fbd268c204f039f"
  },
  "name": "Butsura",
  "year": 1861,
  "reclat": 27.08333,
  "reclong": 84.08333
},
{
  "_id": {
    "$oid": "656a815c9fbd268c204f03a1"
  },
  "name": "Cabezo de Mayo",
  "year": 1870,
  "reclat": 37.98333,
  "reclong": -1.16667
},
{
  "_id": {
    "$oid": "656a815c9fbd268c204f03a2"
  },
  "name": "Cabin Creek",
  "year": 1886,
  "reclat": 35.5,
  "reclong": -93.5
},
{
  "_id": {
    "$oid": "656a815c9fbd268c204f03a8"
  },
  "name": "Cañellas",
  "year": 1861,
  "reclat": 41.25,
  "reclong": 1.66667
},
{
  "_id": {
    "$oid": "656a815c9fbd268c204f03a9"
  },
  "name": "Cangas de Onis",
  "year": 1866,
  "reclat": 43.38333,
  "reclong": -5.15
},
{
  "_id": {
    "$oid": "656a815c9fbd268c204f03ab"
  },
  "name": "Cape Girardeau",
  "year": 1846,
  "reclat": 37.26667,
  "reclong": -89.58333
},
{
  "_id": {
    "$oid": "656a815c9fbd268c204f03af"
  },
  "name": "Castalia",
  "year": 1874,
  "reclat": 36.08333,
  "reclong": -78.06667
},
{
  "_id": {
    "$oid": "656a815c9fbd268c204f03b1"
  },
  "name": "Castine",
  "year": 1848,
  "reclat": 44.38333,
  "reclong": -68.75
},
{
  "_id": {
    "$oid": "656a815c9fbd268c204f03b3"
  },
  "name": "Caswell County",
  "year": 1810,
  "reclat": 36.5,
  "reclong": -79.25
},
{
  "_id": {
    "$oid": "656a815c9fbd268c204f03b6"
  },
  "name": "Cereseto",
  "year": 1840,
  "reclat": 45.08333,
  "reclong": 8.3
},
{
  "_id": {
    "$oid": "656a815c9fbd268c204f03b8"
  },
  "name": "Chail",
  "year": 1814,
  "reclat": 25.36667,
  "reclong": 81.66667
},
{
  "_id": {
    "$oid": "656a815c9fbd268c204f03bb"
  },
  "name": "Chandakapur",
  "year": 1838,
  "reclat": 20.26667,
  "reclong": 76.01667
},
{
  "_id": {
    "$oid": "656a815c9fbd268c204f03bc"
  },
  "name": "Chandpur",
  "year": 1885,
  "reclat": 27.28333,
  "reclong": 79.05
},
{
  "_id": {
    "$oid": "656a815c9fbd268c204f03be"
  },
  "name": "Chantonnay",
  "year": 1812,
  "reclat": 46.68333,
  "reclong": 1.05
},
{
  "_id": {
    "$oid": "656a815c9fbd268c204f03bf"
  },
  "name": "Charlotte",
  "year": 1835,
  "reclat": 36.16667,
  "reclong": -87.33333
},
{
  "_id": {
    "$oid": "656a815c9fbd268c204f03c0"
  },
  "name": "Charsonville",
  "year": 1810,
  "reclat": 47.93333,
  "reclong": 1.56667
},
{
  "_id": {
    "$oid": "656a815c9fbd268c204f03c1"
  },
  "name": "Charwallas",
  "year": 1834,
  "reclat": 29.48333,
  "reclong": 75.5
},
{
  "_id": {
    "$oid": "656a815c9fbd268c204f03c2"
  },
  "name": "Chassigny",
  "year": 1815,
  "reclat": 47.71667,
  "reclong": 5.36667
},
{
  "_id": {
    "$oid": "656a815c9fbd268c204f03c3"
  },
  "name": "Château-Renard",
  "year": 1841,
  "reclat": 47.93333,
  "reclong": 2.91667
},
{
  "_id": {
    "$oid": "656a815c9fbd268c204f03cc"
  },
  "name": "Chetrinahatti",
  "year": 1880,
  "reclat": 14.5,
  "reclong": 76.5
},
{
  "_id": {
    "$oid": "656a815c9fbd268c204f03d6"
  },
  "name": "Cold Bokkeveld",
  "year": 1838,
  "reclat": -33.13333,
  "reclong": 19.38333
},
{
  "_id": {
    "$oid": "656a815c9fbd268c204f03d8"
  },
  "name": "Collescipoli",
  "year": 1890,
  "reclat": 42.53333,
  "reclong": 12.61667
},
{
  "_id": {
    "$oid": "656a815c9fbd268c204f03da"
  },
  "name": "Cosina",
  "year": 1844,
  "reclat": 21.16667,
  "reclong": -100.86667
},
{
  "_id": {
    "$oid": "656a815c9fbd268c204f03dd"
  },
  "name": "Cronstad",
  "year": 1877,
  "reclat": -27.7,
  "reclong": 27.3
},
{
  "_id": {
    "$oid": "656a815c9fbd268c204f03de"
  },
  "name": "Cross Roads",
  "year": 1892,
  "reclat": 35.63333,
  "reclong": -78.13333
},
{
  "_id": {
    "$oid": "656a815c9fbd268c204f03e1"
  },
  "name": "Cynthiana",
  "year": 1877,
  "reclat": 38.4,
  "reclong": -84.25
},
{
  "_id": {
    "$oid": "656a815c9fbd268c204f03e3"
  },
  "name": "Dandapur",
  "year": 1878,
  "reclat": 26.91667,
  "reclong": 83.96667
},
{
  "_id": {
    "$oid": "656a815c9fbd268c204f03e4"
  },
  "name": "Daniel's Kuil",
  "year": 1868,
  "reclat": -28.2,
  "reclong": 24.56667
},
{
  "_id": {
    "$oid": "656a815c9fbd268c204f03e5"
  },
  "name": "Danville",
  "year": 1868,
  "reclat": 34.4,
  "reclong": -87.06667
},
{
  "_id": {
    "$oid": "656a815c9fbd268c204f03e6"
  },
  "name": "Darmstadt",
  "year": 1804,
  "reclat": 49.86667,
  "reclong": 8.65
},
{
  "_id": {
    "$oid": "656a815c9fbd268c204f03e9"
  },
  "name": "De Cewsville",
  "year": 1887,
  "reclat": 43,
  "reclong": -80
},
{
  "_id": {
    "$oid": "656a815c9fbd268c204f03ea"
  },
  "name": "Deal",
  "year": 1829,
  "reclat": 40.25,
  "reclong": -74
},
{
  "_id": {
    "$oid": "656a815c9fbd268c204f03eb"
  },
  "name": "Delhi",
  "year": 1897,
  "reclat": 28.56667,
  "reclong": 77.25
},
{
  "_id": {
    "$oid": "656a815c9fbd268c204f03f3"
  },
  "name": "Dharwar",
  "year": 1848,
  "reclat": 14.88333,
  "reclong": 75.6
},
{
  "_id": {
    "$oid": "656a815c9fbd268c204f03f4"
  },
  "name": "Dhurmsala",
  "year": 1860,
  "reclat": 32.23333,
  "reclong": 76.46667
},
{
  "_id": {
    "$oid": "656a815c9fbd268c204f03f8"
  },
  "name": "Djati-Pengilon",
  "year": 1884,
  "reclat": -7.5,
  "reclong": 111.5
},
{
  "_id": {
    "$oid": "656a815c9fbd268c204f03fc"
  },
  "name": "Dolgovoli",
  "year": 1864,
  "reclat": 50.75,
  "reclong": 25.3
},
{
  "_id": {
    "$oid": "656a815c9fbd268c204f03ff"
  },
  "name": "Donga Kohrod",
  "year": 1899,
  "reclat": 21.86667,
  "reclong": 82.45
},
{
  "_id": {
    "$oid": "656a815c9fbd268c204f0401"
  },
  "name": "Doroninsk",
  "year": 1805,
  "reclat": 51.2,
  "reclong": 112.3
},
{
  "_id": {
    "$oid": "656a815c9fbd268c204f0405"
  },
  "name": "Drake Creek",
  "year": 1827,
  "reclat": 36.4,
  "reclong": -86.5
},
{
  "_id": {
    "$oid": "656a815c9fbd268c204f0409"
  },
  "name": "Dundrum",
  "year": 1865,
  "reclat": 52.55,
  "reclong": -8.03333
},
{
  "_id": {
    "$oid": "656a815c9fbd268c204f040b"
  },
  "name": "Durala",
  "year": 1815,
  "reclat": 30.3,
  "reclong": 76.63333
},
{
  "_id": {
    "$oid": "656a815c9fbd268c204f040c"
  },
  "name": "Duruma",
  "year": 1853,
  "reclat": -4,
  "reclong": 39.5
},
{
  "_id": {
    "$oid": "656a815c9fbd268c204f040f"
  },
  "name": "Dyalpur",
  "year": 1872,
  "reclat": 26.25,
  "reclong": 82
},
{
  "_id": {
    "$oid": "656a815c9fbd268c204f041d"
  },
  "name": "Emmaville",
  "year": 1900,
  "reclat": -29.46667,
  "reclong": 151.61667
},
{
  "_id": {
    "$oid": "656a815c9fbd268c204f0420"
  },
  "name": "Épinal",
  "year": 1822,
  "reclat": 48.18333,
  "reclong": 6.46667
},
{
  "_id": {
    "$oid": "656a815c9fbd268c204f0423"
  },
  "name": "Ergheo",
  "year": 1889,
  "reclat": 1.16667,
  "reclong": 44.16667
},
{
  "_id": {
    "$oid": "656a815c9fbd268c204f0424"
  },
  "name": "Erxleben",
  "year": 1812,
  "reclat": 52.21667,
  "reclong": 11.25
},
{
  "_id": {
    "$oid": "656a815c9fbd268c204f0425"
  },
  "name": "Esnandes",
  "year": 1837,
  "reclat": 46.25,
  "reclong": -1.1
},
{
  "_id": {
    "$oid": "656a815c9fbd268c204f0427"
  },
  "name": "Estherville",
  "year": 1879,
  "reclat": 43.41667,
  "reclong": -94.83333
},
{
  "_id": {
    "$oid": "656a815c9fbd268c204f0428"
  },
  "name": "Farmington",
  "year": 1890,
  "reclat": 39.75,
  "reclong": -97.03333
},
{
  "_id": {
    "$oid": "656a815c9fbd268c204f042a"
  },
  "name": "Favars",
  "year": 1844,
  "reclat": 44.38333,
  "reclong": 2.81667
},
{
  "_id": {
    "$oid": "656a815c9fbd268c204f042c"
  },
  "name": "Feid Chair",
  "year": 1875,
  "reclat": 36.88333,
  "reclong": 8.45
},
{
  "_id": {
    "$oid": "656a815c9fbd268c204f042d"
  },
  "name": "Felix",
  "year": 1900,
  "reclat": 32.53333,
  "reclong": -87.16667
},
{
  "_id": {
    "$oid": "656a815c9fbd268c204f042f"
  },
  "name": "Ferguson",
  "year": 1889,
  "reclat": 36.1,
  "reclong": -81.41667
},
{
  "_id": {
    "$oid": "656a815c9fbd268c204f0431"
  },
  "name": "Fisher",
  "year": 1894,
  "reclat": 47.81667,
  "reclong": -96.85
},
{
  "_id": {
    "$oid": "656a815c9fbd268c204f0433"
  },
  "name": "Forest City",
  "year": 1890,
  "reclat": 43.25,
  "reclong": -93.66667
},
{
  "_id": {
    "$oid": "656a815c9fbd268c204f0436"
  },
  "name": "Forsbach",
  "year": 1900,
  "reclat": 50.95,
  "reclong": 7.31667
},
{
  "_id": {
    "$oid": "656a815c9fbd268c204f0437"
  },
  "name": "Forsyth",
  "year": 1829,
  "reclat": 33.01667,
  "reclong": -83.96667
},
{
  "_id": {
    "$oid": "656a815c9fbd268c204f0439"
  },
  "name": "Frankfort (stone)",
  "year": 1868,
  "reclat": 34.48333,
  "reclong": -87.83333
},
{
  "_id": {
    "$oid": "656a815c9fbd268c204f043b"
  },
  "name": "Fukutomi",
  "year": 1882,
  "reclat": 33.18333,
  "reclong": 130.2
},
{
  "_id": {
    "$oid": "656a815c9fbd268c204f043d"
  },
  "name": "Futtehpur",
  "year": 1822,
  "reclat": 25.95,
  "reclong": 80.81667
},
{
  "_id": {
    "$oid": "656a815c9fbd268c204f043f"
  },
  "name": "Galapian",
  "year": 1826,
  "reclat": 44.3,
  "reclong": 0.4
},
{
  "_id": {
    "$oid": "656a815c9fbd268c204f0443"
  },
  "name": "Gambat",
  "year": 1897,
  "reclat": 27.35,
  "reclong": 68.53333
},
{
  "_id": {
    "$oid": "656a815c9fbd268c204f044b"
  },
  "name": "Girgenti",
  "year": 1853,
  "reclat": 37.31667,
  "reclong": 13.56667
},
{
  "_id": {
    "$oid": "656a815c9fbd268c204f0451"
  },
  "name": "Gnadenfrei",
  "year": 1879,
  "reclat": 50.66667,
  "reclong": 16.76667
},
{
  "_id": {
    "$oid": "656a815c9fbd268c204f0452"
  },
  "name": "Gopalpur",
  "year": 1865,
  "reclat": 24.23333,
  "reclong": 89.05
},
{
  "_id": {
    "$oid": "656a815c9fbd268c204f0457"
  },
  "name": "Grosnaja",
  "year": 1861,
  "reclat": 43.66667,
  "reclong": 45.38333
},
{
  "_id": {
    "$oid": "656a815c9fbd268c204f0458"
  },
  "name": "Gross-Divina",
  "year": 1837,
  "reclat": 49.26667,
  "reclong": 18.71667
},
{
  "_id": {
    "$oid": "656a815c9fbd268c204f0459"
  },
  "name": "Grossliebenthal",
  "year": 1881,
  "reclat": 46.35,
  "reclong": 30.58333
},
{
  "_id": {
    "$oid": "656a815c9fbd268c204f045a"
  },
  "name": "Grüneberg",
  "year": 1841,
  "reclat": 51.93333,
  "reclong": 15.5
},
{
  "_id": {
    "$oid": "656a815c9fbd268c204f0460"
  },
  "name": "Guareña",
  "year": 1892,
  "reclat": 38.73333,
  "reclong": -6.01667
},
{
  "_id": {
    "$oid": "656a815c9fbd268c204f0461"
  },
  "name": "Guêa",
  "year": 1891,
  "reclat": 43.76667,
  "reclong": 20.23333
},
{
  "_id": {
    "$oid": "656a815c9fbd268c204f0467"
  },
  "name": "Gurram Konda",
  "year": 1814,
  "reclat": 13.78333,
  "reclong": 78.56667
},
{
  "_id": {
    "$oid": "656a815c9fbd268c204f0469"
  },
  "name": "Gütersloh",
  "year": 1851,
  "reclat": 51.91667,
  "reclong": 8.38333
},
{
  "_id": {
    "$oid": "656a815c9fbd268c204f046b"
  },
  "name": "Hachi-oji",
  "year": 1817,
  "reclat": 35.65,
  "reclong": 139.33333
},
{
  "_id": {
    "$oid": "656a815c9fbd268c204f046f"
  },
  "name": "Haraiya",
  "year": 1878,
  "reclat": 26.8,
  "reclong": 82.53333
},
{
  "_id": {
    "$oid": "656a815c9fbd268c204f0472"
  },
  "name": "Harrison County",
  "year": 1859,
  "reclat": 38.25,
  "reclong": -86.16667
},
{
  "_id": {
    "$oid": "656a815c9fbd268c204f0474"
  },
  "name": "Hassi-Jekna",
  "year": 1890,
  "reclat": 28.95,
  "reclong": 0.81667
},
{
  "_id": {
    "$oid": "656a815c9fbd268c204f0479"
  },
  "name": "Heredia",
  "year": 1857,
  "reclat": 10,
  "reclong": -84.1
},
{
  "_id": {
    "$oid": "656a815c9fbd268c204f047a"
  },
  "name": "Hessle",
  "year": 1869,
  "reclat": 59.85,
  "reclong": 17.66667
},
{
  "_id": {
    "$oid": "656a815c9fbd268c204f047b"
  },
  "name": "Higashi-koen",
  "year": 1897,
  "reclat": 33.6,
  "reclong": 130.43333
},
{
  "_id": {
    "$oid": "656a815c9fbd268c204f047c"
  },
  "name": "High Possil",
  "year": 1804,
  "reclat": 55.9,
  "reclong": -4.23333
},
{
  "_id": {
    "$oid": "656a815c9fbd268c204f0482"
  },
  "name": "Homestead",
  "year": 1875,
  "reclat": 41.8,
  "reclong": -91.86667
},
{
  "_id": {
    "$oid": "656a815c9fbd268c204f0483"
  },
  "name": "Honolulu",
  "year": 1825,
  "reclat": 21.3,
  "reclong": -157.86667
},
{
  "_id": {
    "$oid": "656a815c9fbd268c204f0488"
  },
  "name": "Hungen",
  "year": 1877,
  "reclat": 50.3,
  "reclong": 8.91667
},
{
  "_id": {
    "$oid": "656a815c9fbd268c204f048a"
  },
  "name": "Ibbenbüren",
  "year": 1870,
  "reclat": 52.28333,
  "reclong": 7.7
},
{
  "_id": {
    "$oid": "656a815c9fbd268c204f0491"
  },
  "name": "Indarch",
  "year": 1891,
  "reclat": 39.75,
  "reclong": 46.66667
},
{
  "_id": {
    "$oid": "656a815c9fbd268c204f0498"
  },
  "name": "Itapicuru-Mirim",
  "year": 1879,
  "reclat": -3.4,
  "reclong": -44.33333
},
{
  "_id": {
    "$oid": "656a815c9fbd268c204f049f"
  },
  "name": "Jamkheir",
  "year": 1866,
  "reclat": 18.75,
  "reclong": 75.33333
},
{
  "_id": {
    "$oid": "656a815c9fbd268c204f04a1"
  },
  "name": "Jelica",
  "year": 1889,
  "reclat": 43.83333,
  "reclong": 20.44167
},
{
  "_id": {
    "$oid": "656a815c9fbd268c204f04a4"
  },
  "name": "Jhung",
  "year": 1873,
  "reclat": 31.3,
  "reclong": 72.38333
},
{
  "_id": {
    "$oid": "656a815c9fbd268c204f04a6"
  },
  "name": "Jianshi",
  "year": 1890,
  "reclat": 30.80833,
  "reclong": 109.5
},
{
  "_id": {
    "$oid": "656a815c9fbd268c204f04a9"
  },
  "name": "Jodzie",
  "year": 1877,
  "reclat": 55.7,
  "reclong": 24.4
},
{
  "_id": {
    "$oid": "656a815c9fbd268c204f04ac"
  },
  "name": "Jonzac",
  "year": 1819,
  "reclat": 45.43333,
  "reclong": -0.45
},
{
  "_id": {
    "$oid": "656a815c9fbd268c204f04ae"
  },
  "name": "Judesegeri",
  "year": 1876,
  "reclat": 12.85,
  "reclong": 76.8
},
{
  "_id": {
    "$oid": "656a815c9fbd268c204f04b2"
  },
  "name": "Juvinas",
  "year": 1821,
  "reclat": 44.71667,
  "reclong": 4.3
},
{
  "_id": {
    "$oid": "656a815c9fbd268c204f04b3"
  },
  "name": "Kaba",
  "year": 1857,
  "reclat": 47.35,
  "reclong": 21.3
},
{
  "_id": {
    "$oid": "656a815c9fbd268c204f04b5"
  },
  "name": "Kadonah",
  "year": 1822,
  "reclat": 27.08333,
  "reclong": 78.33333
},
{
  "_id": {
    "$oid": "656a815c9fbd268c204f04b6"
  },
  "name": "Kaee",
  "year": 1838,
  "reclat": 27.25,
  "reclong": 79.96667
},
{
  "_id": {
    "$oid": "656a815c9fbd268c204f04ba"
  },
  "name": "Kakangari",
  "year": 1890,
  "reclat": 12.38333,
  "reclong": 78.51667
},
{
  "_id": {
    "$oid": "656a815c9fbd268c204f04bb"
  },
  "name": "Kakowa",
  "year": 1858,
  "reclat": 45.13333,
  "reclong": 21.66667
},
{
  "_id": {
    "$oid": "656a815c9fbd268c204f04bd"
  },
  "name": "Kalumbi",
  "year": 1879,
  "reclat": 17.83333,
  "reclong": 73.98333
},
{
  "_id": {
    "$oid": "656a815c9fbd268c204f04c3"
  },
  "name": "Kangra Valley",
  "year": 1897,
  "reclat": 32.08333,
  "reclong": 76.3
},
{
  "_id": {
    "$oid": "656a815c9fbd268c204f04c7"
  },
  "name": "Karakol",
  "year": 1840,
  "reclat": 47.21667,
  "reclong": 81.01667
},
{
  "_id": {
    "$oid": "656a815c9fbd268c204f04d6"
  },
  "name": "Kerilis",
  "year": 1874,
  "reclat": 48.4,
  "reclong": -3.3
},
{
  "_id": {
    "$oid": "656a815c9fbd268c204f04d7"
  },
  "name": "Kernouve",
  "year": 1869,
  "reclat": 48.11667,
  "reclong": -3.08333
},
{
  "_id": {
    "$oid": "656a815c9fbd268c204f04d8"
  },
  "name": "Kesen",
  "year": 1850,
  "reclat": 38.98333,
  "reclong": 141.61667
},
{
  "_id": {
    "$oid": "656a815c9fbd268c204f04d9"
  },
  "name": "Khairpur",
  "year": 1873,
  "reclat": 29.53333,
  "reclong": 72.3
},
{
  "_id": {
    "$oid": "656a815c9fbd268c204f04dc"
  },
  "name": "Kheragur",
  "year": 1860,
  "reclat": 26.95,
  "reclong": 77.88333
},
{
  "_id": {
    "$oid": "656a815c9fbd268c204f04dd"
  },
  "name": "Khetri",
  "year": 1867,
  "reclat": 28.01667,
  "reclong": 75.81667
},
{
  "_id": {
    "$oid": "656a815c9fbd268c204f04e5"
  },
  "name": "Kikino",
  "year": 1809,
  "reclat": 55,
  "reclong": 34
},
{
  "_id": {
    "$oid": "656a815c9fbd268c204f04e8"
  },
  "name": "Killeter",
  "year": 1844,
  "reclat": 54.66667,
  "reclong": -7.66667
},
{
  "_id": {
    "$oid": "656a815c9fbd268c204f04ed"
  },
  "name": "Klein-Wenden",
  "year": 1843,
  "reclat": 51.6,
  "reclong": 10.8
},
{
  "_id": {
    "$oid": "656a815c9fbd268c204f04ee"
  },
  "name": "Knyahinya",
  "year": 1866,
  "reclat": 48.9,
  "reclong": 22.4
},
{
  "_id": {
    "$oid": "656a815c9fbd268c204f04f4"
  },
  "name": "Krähenberg",
  "year": 1869,
  "reclat": 49.32694,
  "reclong": 7.46472
},
{
  "_id": {
    "$oid": "656a815c9fbd268c204f04f5"
  },
  "name": "Krasnoi-Ugol",
  "year": 1829,
  "reclat": 54.03333,
  "reclong": 40.9
},
{
  "_id": {
    "$oid": "656a815c9fbd268c204f04fb"
  },
  "name": "Kuleschovka",
  "year": 1811,
  "reclat": 50.75,
  "reclong": 33.5
},
{
  "_id": {
    "$oid": "656a815c9fbd268c204f0500"
  },
  "name": "Kusiali",
  "year": 1860,
  "reclat": 29.68333,
  "reclong": 78.38333
},
{
  "_id": {
    "$oid": "656a815c9fbd268c204f0504"
  },
  "name": "Kyushu",
  "year": 1886,
  "reclat": 32.03333,
  "reclong": 130.63333
},
{
  "_id": {
    "$oid": "656a815c9fbd268c204f0505"
  },
  "name": "La Bécasse",
  "year": 1879,
  "reclat": 47.08333,
  "reclong": 1.75
},
{
  "_id": {
    "$oid": "656a815c9fbd268c204f0506"
  },
  "name": "La Charca",
  "year": 1878,
  "reclat": 20.66667,
  "reclong": -101.28333
},
{
  "_id": {
    "$oid": "656a815c9fbd268c204f0509"
  },
  "name": "Laborel",
  "year": 1871,
  "reclat": 44.28333,
  "reclong": 5.58333
},
{
  "_id": {
    "$oid": "656a815c9fbd268c204f050b"
  },
  "name": "L'Aigle",
  "year": 1803,
  "reclat": 48.76667,
  "reclong": 0.63333
},
{
  "_id": {
    "$oid": "656a815c9fbd268c204f050e"
  },
  "name": "Lalitpur",
  "year": 1887,
  "reclat": 24.45,
  "reclong": 78.56667
},
{
  "_id": {
    "$oid": "656a815c9fbd268c204f050f"
  },
  "name": "Lancé",
  "year": 1872,
  "reclat": 47.7,
  "reclong": 1.06667
},
{
  "_id": {
    "$oid": "656a815c9fbd268c204f0510"
  },
  "name": "Lancon",
  "year": 1897,
  "reclat": 43.75,
  "reclong": 5.11667
},
{
  "_id": {
    "$oid": "656a815c9fbd268c204f0515"
  },
  "name": "Launton",
  "year": 1830,
  "reclat": 51.9,
  "reclong": -1.11667
},
{
  "_id": {
    "$oid": "656a815c9fbd268c204f0517"
  },
  "name": "Le Pressoir",
  "year": 1845,
  "reclat": 47.16667,
  "reclong": 0.43333
},
{
  "_id": {
    "$oid": "656a815c9fbd268c204f0518"
  },
  "name": "Le Teilleul",
  "year": 1845,
  "reclat": 48.53333,
  "reclong": -0.86667
},
{
  "_id": {
    "$oid": "656a815c9fbd268c204f051d"
  },
  "name": "Leonovka",
  "year": 1900,
  "reclat": 52.26667,
  "reclong": 32.85
},
{
  "_id": {
    "$oid": "656a815c9fbd268c204f051e"
  },
  "name": "Les Ormes",
  "year": 1857,
  "reclat": 48.35,
  "reclong": 3.25
},
{
  "_id": {
    "$oid": "656a815c9fbd268c204f051f"
  },
  "name": "Lesves",
  "year": 1896,
  "reclat": 50.36667,
  "reclong": 4.73333
},
{
  "_id": {
    "$oid": "656a815c9fbd268c204f0522"
  },
  "name": "Limerick",
  "year": 1813,
  "reclat": 52.56667,
  "reclong": -8.78333
},
{
  "_id": {
    "$oid": "656a815c9fbd268c204f0523"
  },
  "name": "Linum",
  "year": 1854,
  "reclat": 52.75,
  "reclong": 12.9
},
{
  "_id": {
    "$oid": "656a815c9fbd268c204f0525"
  },
  "name": "Lissa",
  "year": 1808,
  "reclat": 50.2,
  "reclong": 14.85
},
{
  "_id": {
    "$oid": "656a815c9fbd268c204f0526"
  },
  "name": "Little Piney",
  "year": 1839,
  "reclat": 37.91667,
  "reclong": -92.08333
},
{
  "_id": {
    "$oid": "656a815c9fbd268c204f0527"
  },
  "name": "Lixna",
  "year": 1820,
  "reclat": 56,
  "reclong": 26.43333
},
{
  "_id": {
    "$oid": "656a815c9fbd268c204f0528"
  },
  "name": "Lodran",
  "year": 1868,
  "reclat": 29.53333,
  "reclong": 71.8
},
{
  "_id": {
    "$oid": "656a815c9fbd268c204f052b"
  },
  "name": "Los Martinez",
  "year": 1894,
  "reclat": 38,
  "reclong": -0.83333
},
{
  "_id": {
    "$oid": "656a815c9fbd268c204f0531"
  },
  "name": "Lumpkin",
  "year": 1869,
  "reclat": 32.03333,
  "reclong": -84.76667
},
{
  "_id": {
    "$oid": "656a815c9fbd268c204f0533"
  },
  "name": "Lundsgård",
  "year": 1889,
  "reclat": 56.21667,
  "reclong": 13.03333
},
{
  "_id": {
    "$oid": "656a815c9fbd268c204f0534"
  },
  "name": "Luotolax",
  "year": 1813,
  "reclat": 61.2,
  "reclong": 27.7
},
{
  "_id": {
    "$oid": "656a815c9fbd268c204f0538"
  },
  "name": "Macau",
  "year": 1836,
  "reclat": -5.2,
  "reclong": -36.66667
},
{
  "_id": {
    "$oid": "656a815c9fbd268c204f053d"
  },
  "name": "Madrid",
  "year": 1896,
  "reclat": 40.41667,
  "reclong": -3.71667
},
{
  "_id": {
    "$oid": "656a815c9fbd268c204f053f"
  },
  "name": "Magnesia",
  "year": 1899,
  "reclat": 37.86667,
  "reclong": 27.51667
},
{
  "_id": {
    "$oid": "656a815c9fbd268c204f0549"
  },
  "name": "Manbhoom",
  "year": 1863,
  "reclat": 23.05,
  "reclong": 86.7
},
{
  "_id": {
    "$oid": "656a815c9fbd268c204f054a"
  },
  "name": "Manegaon",
  "year": 1843,
  "reclat": 20.96667,
  "reclong": 76.1
},
{
  "_id": {
    "$oid": "656a815c9fbd268c204f054f"
  },
  "name": "Mariaville",
  "year": 1898,
  "reclat": 42.71667,
  "reclong": -99.38333
},
{
  "_id": {
    "$oid": "656a815c9fbd268c204f0553"
  },
  "name": "Marion (Iowa)",
  "year": 1847,
  "reclat": 41.9,
  "reclong": -91.6
},
{
  "_id": {
    "$oid": "656a815c9fbd268c204f0555"
  },
  "name": "Marmande",
  "year": 1848,
  "reclat": 44.5,
  "reclong": 0.15
},
{
  "_id": {
    "$oid": "656a815c9fbd268c204f0558"
  },
  "name": "Mascombes",
  "year": 1836,
  "reclat": 45.36667,
  "reclong": 1.86667
},
{
  "_id": {
    "$oid": "656a815c9fbd268c204f055a"
  },
  "name": "Mässing",
  "year": 1803,
  "reclat": 48.13333,
  "reclong": 12.61667
},
{
  "_id": {
    "$oid": "656a815c9fbd268c204f055c"
  },
  "name": "Mauritius",
  "year": 1801,
  "reclat": -20,
  "reclong": 57
},
{
  "_id": {
    "$oid": "656a815c9fbd268c204f055e"
  },
  "name": "Mazapil",
  "year": 1885,
  "reclat": 24.68333,
  "reclong": -101.68333
},
{
  "_id": {
    "$oid": "656a815c9fbd268c204f0562"
  },
  "name": "Meerut",
  "year": 1861,
  "reclat": 29.01667,
  "reclong": 77.8
},
{
  "_id": {
    "$oid": "656a815c9fbd268c204f0564"
  },
  "name": "Menow",
  "year": 1862,
  "reclat": 53.18333,
  "reclong": 13.15
},
{
  "_id": {
    "$oid": "656a815c9fbd268c204f0566"
  },
  "name": "Mern",
  "year": 1878,
  "reclat": 55.05,
  "reclong": 12.06667
},
{
  "_id": {
    "$oid": "656a815c9fbd268c204f056a"
  },
  "name": "Meuselbach",
  "year": 1897,
  "reclat": 50.58333,
  "reclong": 11.1
},
{
  "_id": {
    "$oid": "656a815c9fbd268c204f056c"
  },
  "name": "Mezö-Madaras",
  "year": 1852,
  "reclat": 46.5,
  "reclong": 25.73333
},
{
  "_id": {
    "$oid": "656a815c9fbd268c204f056d"
  },
  "name": "Mhow",
  "year": 1827,
  "reclat": 25.9,
  "reclong": 83.61667
},
{
  "_id": {
    "$oid": "656a815c9fbd268c204f056f"
  },
  "name": "Middlesbrough",
  "year": 1881,
  "reclat": 54.56667,
  "reclong": -1.16667
},
{
  "_id": {
    "$oid": "656a815c9fbd268c204f0571"
  },
  "name": "Mighei",
  "year": 1889,
  "reclat": 48.06667,
  "reclong": 30.96667
},
{
  "_id": {
    "$oid": "656a815c9fbd268c204f0574"
  },
  "name": "Milena",
  "year": 1842,
  "reclat": 46.18333,
  "reclong": 16.1
},
{
  "_id": {
    "$oid": "656a815c9fbd268c204f0578"
  },
  "name": "Mineo",
  "year": 1826,
  "reclat": 37.28333,
  "reclong": 14.7
},
{
  "_id": {
    "$oid": "656a815c9fbd268c204f057c"
  },
  "name": "Misshof",
  "year": 1890,
  "reclat": 56.66667,
  "reclong": 23
},
{
  "_id": {
    "$oid": "656a815c9fbd268c204f057d"
  },
  "name": "Mjelleim",
  "year": 1898,
  "reclat": 61.73333,
  "reclong": 5.93333
},
{
  "_id": {
    "$oid": "656a815c9fbd268c204f057e"
  },
  "name": "Mocs",
  "year": 1882,
  "reclat": 46.8,
  "reclong": 24.03333
},
{
  "_id": {
    "$oid": "656a815c9fbd268c204f0581"
  },
  "name": "Molina",
  "year": 1858,
  "reclat": 38.11667,
  "reclong": -1.16667
},
{
  "_id": {
    "$oid": "656a815c9fbd268c204f0584"
  },
  "name": "Monroe",
  "year": 1849,
  "reclat": 35.25,
  "reclong": -80.5
},
{
  "_id": {
    "$oid": "656a815c9fbd268c204f0586"
  },
  "name": "Monte Milone",
  "year": 1846,
  "reclat": 43.26667,
  "reclong": 13.35
},
{
  "_id": {
    "$oid": "656a815c9fbd268c204f0588"
  },
  "name": "Montlivault",
  "year": 1838,
  "reclat": 47.63333,
  "reclong": 1.58333
},
{
  "_id": {
    "$oid": "656a815c9fbd268c204f058b"
  },
  "name": "Mooresfort",
  "year": 1810,
  "reclat": 52.45,
  "reclong": -8.33333
},
{
  "_id": {
    "$oid": "656a815c9fbd268c204f058d"
  },
  "name": "Moradabad",
  "year": 1808,
  "reclat": 28.78333,
  "reclong": 78.83333
},
{
  "_id": {
    "$oid": "656a815c9fbd268c204f058f"
  },
  "name": "Mornans",
  "year": 1875,
  "reclat": 44.6,
  "reclong": 5.13333
},
{
  "_id": {
    "$oid": "656a815c9fbd268c204f0591"
  },
  "name": "Moti-ka-nagla",
  "year": 1868,
  "reclat": 26.83333,
  "reclong": 77.33333
},
{
  "_id": {
    "$oid": "656a815c9fbd268c204f0592"
  },
  "name": "Motta di Conti",
  "year": 1868,
  "reclat": 45.2,
  "reclong": 8.5
},
{
  "_id": {
    "$oid": "656a815c9fbd268c204f0597"
  },
  "name": "Muddoor",
  "year": 1865,
  "reclat": 12.63333,
  "reclong": 77.01667
},
{
  "_id": {
    "$oid": "656a815c9fbd268c204f059d"
  },
  "name": "Myhee Caunta",
  "year": 1842,
  "reclat": 23.05,
  "reclong": 72.63333
},
{
  "_id": {
    "$oid": "656a815c9fbd268c204f05a0"
  },
  "name": "Nagaria",
  "year": 1875,
  "reclat": 26.98333,
  "reclong": 78.21667
},
{
  "_id": {
    "$oid": "656a815c9fbd268c204f05a1"
  },
  "name": "Nagy-Borové",
  "year": 1895,
  "reclat": 49.16667,
  "reclong": 19.5
},
{
  "_id": {
    "$oid": "656a815c9fbd268c204f05a4"
  },
  "name": "Nammianthal",
  "year": 1886,
  "reclat": 12.28333,
  "reclong": 79.2
},
{
  "_id": {
    "$oid": "656a815c9fbd268c204f05a6"
  },
  "name": "Nanjemoy",
  "year": 1825,
  "reclat": 38.41667,
  "reclong": -77.16667
},
{
  "_id": {
    "$oid": "656a815c9fbd268c204f05ae"
  },
  "name": "Nawapali",
  "year": 1890,
  "reclat": 21.25,
  "reclong": 83.66667
},
{
  "_id": {
    "$oid": "656a815c9fbd268c204f05b0"
  },
  "name": "Nedagolla",
  "year": 1870,
  "reclat": 18.68333,
  "reclong": 83.48333
},
{
  "_id": {
    "$oid": "656a815c9fbd268c204f05b2"
  },
  "name": "Nerft",
  "year": 1864,
  "reclat": 56.5,
  "reclong": 21.5
},
{
  "_id": {
    "$oid": "656a815c9fbd268c204f05b4"
  },
  "name": "New Concord",
  "year": 1860,
  "reclat": 40,
  "reclong": -81.76667
},
{
  "_id": {
    "$oid": "656a815c9fbd268c204f05b7"
  },
  "name": "Ngawi",
  "year": 1883,
  "reclat": -7.45,
  "reclong": 111.41667
},
{
  "_id": {
    "$oid": "656a815c9fbd268c204f05b8"
  },
  "name": "N'Goureyma",
  "year": 1900,
  "reclat": 13.85,
  "reclong": -4.38333
},
{
  "_id": {
    "$oid": "656a815c9fbd268c204f05c0"
  },
  "name": "Nio",
  "year": 1897,
  "reclat": 34.2,
  "reclong": 131.56667
},
{
  "_id": {
    "$oid": "656a815c9fbd268c204f05c2"
  },
  "name": "Nobleborough",
  "year": 1823,
  "reclat": 44.08333,
  "reclong": -69.48333
},
{
  "_id": {
    "$oid": "656a815c9fbd268c204f05c5"
  },
  "name": "Nogoya",
  "year": 1879,
  "reclat": -32.36667,
  "reclong": -59.83333
},
{
  "_id": {
    "$oid": "656a815c9fbd268c204f05c9"
  },
  "name": "Novo-Urei",
  "year": 1886,
  "reclat": 54.81667,
  "reclong": 46
},
{
  "_id": {
    "$oid": "656a815c9fbd268c204f05ce"
  },
  "name": "Nulles",
  "year": 1851,
  "reclat": 41.63333,
  "reclong": 0.75
},
{
  "_id": {
    "$oid": "656a815c9fbd268c204f05d2"
  },
  "name": "Ochansk",
  "year": 1887,
  "reclat": 57.78333,
  "reclong": 55.26667
},
{
  "_id": {
    "$oid": "656a815c9fbd268c204f05d4"
  },
  "name": "Oesel",
  "year": 1855,
  "reclat": 58.5,
  "reclong": 23
},
{
  "_id": {
    "$oid": "656a815c9fbd268c204f05d5"
  },
  "name": "Ofehértó",
  "year": 1900,
  "reclat": 47.88333,
  "reclong": 22.03333
},
{
  "_id": {
    "$oid": "656a815c9fbd268c204f05d7"
  },
  "name": "Ohaba",
  "year": 1857,
  "reclat": 46.06667,
  "reclong": 23.58333
},
{
  "_id": {
    "$oid": "656a815c9fbd268c204f05dc"
  },
  "name": "Okniny",
  "year": 1834,
  "reclat": 50.83333,
  "reclong": 25.5
},
{
  "_id": {
    "$oid": "656a815c9fbd268c204f05e2"
  },
  "name": "Orgueil",
  "year": 1864,
  "reclat": 43.88333,
  "reclong": 1.38333
},
{
  "_id": {
    "$oid": "656a815c9fbd268c204f05e4"
  },
  "name": "Ornans",
  "year": 1868,
  "reclat": 47.11667,
  "reclong": 6.15
},
{
  "_id": {
    "$oid": "656a815c9fbd268c204f05e6"
  },
  "name": "Orvinio",
  "year": 1872,
  "reclat": 42.13333,
  "reclong": 12.93333
},
{
  "_id": {
    "$oid": "656a815c9fbd268c204f05e8"
  },
  "name": "Otomi",
  "year": 1867,
  "reclat": 38.4,
  "reclong": 140.35
},
{
  "_id": {
    "$oid": "656a815c9fbd268c204f05e9"
  },
  "name": "Ottawa",
  "year": 1896,
  "reclat": 38.6,
  "reclong": -95.21667
},
{
  "_id": {
    "$oid": "656a815c9fbd268c204f05ee"
  },
  "name": "Ovambo",
  "year": 1900,
  "reclat": -18,
  "reclong": 16
},
{
  "_id": {
    "$oid": "656a815c9fbd268c204f05ef"
  },
  "name": "Oviedo",
  "year": 1856,
  "reclat": 43.4,
  "reclong": -5.86667
},
{
  "_id": {
    "$oid": "656a815c9fbd268c204f05f1"
  },
  "name": "Pacula",
  "year": 1881,
  "reclat": 21.05,
  "reclong": -99.3
},
{
  "_id": {
    "$oid": "656a815c9fbd268c204f05fa"
  },
  "name": "Pampanga",
  "year": 1859,
  "reclat": 15.08333,
  "reclong": 120.7
},
{
  "_id": {
    "$oid": "656a815c9fbd268c204f0600"
  },
  "name": "Parnallee",
  "year": 1857,
  "reclat": 9.23333,
  "reclong": 78.35
},
{
  "_id": {
    "$oid": "656a815c9fbd268c204f0609"
  },
  "name": "Pavlograd",
  "year": 1826,
  "reclat": 48.53333,
  "reclong": 35.98333
},
{
  "_id": {
    "$oid": "656a815c9fbd268c204f060a"
  },
  "name": "Pavlovka",
  "year": 1882,
  "reclat": 52.03333,
  "reclong": 43
},
{
  "_id": {
    "$oid": "656a815c9fbd268c204f0610"
  },
  "name": "Peramiho",
  "year": 1899,
  "reclat": -10.66667,
  "reclong": 35.5
},
{
  "_id": {
    "$oid": "656a815c9fbd268c204f0612"
  },
  "name": "Perth",
  "year": 1830,
  "reclat": 56.4,
  "reclong": -3.43333
},
{
  "_id": {
    "$oid": "656a815c9fbd268c204f0616"
  },
  "name": "Petersburg",
  "year": 1855,
  "reclat": 35.3,
  "reclong": -86.63333
},
{
  "_id": {
    "$oid": "656a815c9fbd268c204f0619"
  },
  "name": "Phu Hong",
  "year": 1887,
  "reclat": 11.25,
  "reclong": 108.58333
},
{
  "_id": {
    "$oid": "656a815c9fbd268c204f061d"
  },
  "name": "Picote",
  "year": 1843,
  "reclat": 41.36667,
  "reclong": -6.23333
},
{
  "_id": {
    "$oid": "656a815c9fbd268c204f061e"
  },
  "name": "Pillistfer",
  "year": 1863,
  "reclat": 58.66667,
  "reclong": 25.73333
},
{
  "_id": {
    "$oid": "656a815c9fbd268c204f0620"
  },
  "name": "Piquetberg",
  "year": 1881,
  "reclat": -32.86667,
  "reclong": 18.71667
},
{
  "_id": {
    "$oid": "656a815c9fbd268c204f0621"
  },
  "name": "Pirgunje",
  "year": 1882,
  "reclat": 25.8,
  "reclong": 88.45
},
{
  "_id": {
    "$oid": "656a815c9fbd268c204f0622"
  },
  "name": "Pirthalla",
  "year": 1884,
  "reclat": 29.58333,
  "reclong": 76
},
{
  "_id": {
    "$oid": "656a815c9fbd268c204f0627"
  },
  "name": "Pnompehn",
  "year": 1868,
  "reclat": 11.58333,
  "reclong": 104.91667
},
{
  "_id": {
    "$oid": "656a815c9fbd268c204f0629"
  },
  "name": "Pohlitz",
  "year": 1819,
  "reclat": 50.93333,
  "reclong": 12.13333
},
{
  "_id": {
    "$oid": "656a815c9fbd268c204f062a"
  },
  "name": "Pokhra",
  "year": 1866,
  "reclat": 26.71667,
  "reclong": 82.66667
},
{
  "_id": {
    "$oid": "656a815c9fbd268c204f0632"
  },
  "name": "Pricetown",
  "year": 1893,
  "reclat": 39.11667,
  "reclong": -83.85
},
{
  "_id": {
    "$oid": "656a815c9fbd268c204f0634"
  },
  "name": "Pulsora",
  "year": 1863,
  "reclat": 23.36667,
  "reclong": 75.18333
},
{
  "_id": {
    "$oid": "656a815c9fbd268c204f0635"
  },
  "name": "Pultusk",
  "year": 1868,
  "reclat": 52.76667,
  "reclong": 21.26667
},
{
  "_id": {
    "$oid": "656a815c9fbd268c204f0636"
  },
  "name": "Punganaru",
  "year": 1811,
  "reclat": 13.33333,
  "reclong": 78.95
},
{
  "_id": {
    "$oid": "656a815c9fbd268c204f063b"
  },
  "name": "Quenggouk",
  "year": 1857,
  "reclat": 17.76667,
  "reclong": 95.18333
},
{
  "_id": {
    "$oid": "656a815c9fbd268c204f063c"
  },
  "name": "Quesa",
  "year": 1898,
  "reclat": 39,
  "reclong": -0.66667
},
{
  "_id": {
    "$oid": "656a815c9fbd268c204f063e"
  },
  "name": "Quincay",
  "year": 1851,
  "reclat": 46.6,
  "reclong": 0.25
},
{
  "_id": {
    "$oid": "656a815c9fbd268c204f0642"
  },
  "name": "Rakovka",
  "year": 1878,
  "reclat": 52.98333,
  "reclong": 37.03333
},
{
  "_id": {
    "$oid": "656a815c9fbd268c204f0647"
  },
  "name": "Rancho de la Presa",
  "year": 1899,
  "reclat": 19.86667,
  "reclong": -100.81667
},
{
  "_id": {
    "$oid": "656a815c9fbd268c204f064c"
  },
  "name": "Ratyn",
  "year": 1880,
  "reclat": 52.2,
  "reclong": 17.98333
},
{
  "_id": {
    "$oid": "656a815c9fbd268c204f0650"
  },
  "name": "Renazzo",
  "year": 1824,
  "reclat": 44.76667,
  "reclong": 11.28333
},
{
  "_id": {
    "$oid": "656a815c9fbd268c204f065a"
  },
  "name": "Richmond",
  "year": 1828,
  "reclat": 37.46667,
  "reclong": -77.5
},
{
  "_id": {
    "$oid": "656a815c9fbd268c204f065d"
  },
  "name": "Rochester",
  "year": 1876,
  "reclat": 41.08333,
  "reclong": -86.28333
},
{
  "_id": {
    "$oid": "656a815c9fbd268c204f065e"
  },
  "name": "Rockhampton",
  "year": 1895,
  "reclat": -23.38333,
  "reclong": 150.51667
},
{
  "_id": {
    "$oid": "656a815c9fbd268c204f065f"
  },
  "name": "Roda",
  "year": 1871,
  "reclat": 42.3,
  "reclong": 0.55
},
{
  "_id": {
    "$oid": "656a815c9fbd268c204f0662"
  },
  "name": "Rowton",
  "year": 1876,
  "reclat": 52.76667,
  "reclong": -2.51667
},
{
  "_id": {
    "$oid": "656a815c9fbd268c204f0667"
  },
  "name": "Sabetmahet",
  "year": 1855,
  "reclat": 27.43333,
  "reclong": 82.08333
},
{
  "_id": {
    "$oid": "656a815c9fbd268c204f0675"
  },
  "name": "Santa Barbara",
  "year": 1873,
  "reclat": -29.2,
  "reclong": -51.86667
},
{
  "_id": {
    "$oid": "656a815c9fbd268c204f067c"
  },
  "name": "Sauguis",
  "year": 1868,
  "reclat": 43.15,
  "reclong": -0.85
},
{
  "_id": {
    "$oid": "656a815c9fbd268c204f067d"
  },
  "name": "Savtschenskoje",
  "year": 1894,
  "reclat": 47.21667,
  "reclong": 29.86667
},
{
  "_id": {
    "$oid": "656a815c9fbd268c204f0682"
  },
  "name": "Schönenberg",
  "year": 1846,
  "reclat": 48.11667,
  "reclong": 10.46667
},
{
  "_id": {
    "$oid": "656a815c9fbd268c204f0683"
  },
  "name": "Searsmont",
  "year": 1871,
  "reclat": 44.36667,
  "reclong": -69.2
},
{
  "_id": {
    "$oid": "656a815c9fbd268c204f0685"
  },
  "name": "Segowlie",
  "year": 1853,
  "reclat": 26.75,
  "reclong": 84.78333
},
{
  "_id": {
    "$oid": "656a815c9fbd268c204f068c"
  },
  "name": "Seres",
  "year": 1818,
  "reclat": 41.05,
  "reclong": 23.56667
},
{
  "_id": {
    "$oid": "656a815c9fbd268c204f068f"
  },
  "name": "Sevilla",
  "year": 1862,
  "reclat": 37.41667,
  "reclong": -6
},
{
  "_id": {
    "$oid": "656a815c9fbd268c204f0690"
  },
  "name": "Sevrukovo",
  "year": 1874,
  "reclat": 50.61667,
  "reclong": 36.6
},
{
  "_id": {
    "$oid": "656a815c9fbd268c204f0692"
  },
  "name": "Shalka",
  "year": 1850,
  "reclat": 23.1,
  "reclong": 87.3
},
{
  "_id": {
    "$oid": "656a815c9fbd268c204f0695"
  },
  "name": "Shergotty",
  "year": 1865,
  "reclat": 24.55,
  "reclong": 84.83333
},
{
  "_id": {
    "$oid": "656a815c9fbd268c204f069a"
  },
  "name": "Shytal",
  "year": 1863,
  "reclat": 24.33333,
  "reclong": 90.16667
},
{
  "_id": {
    "$oid": "656a815c9fbd268c204f06a4"
  },
  "name": "Sitathali",
  "year": 1875,
  "reclat": 20.91667,
  "reclong": 82.58333
},
{
  "_id": {
    "$oid": "656a815c9fbd268c204f06a7"
  },
  "name": "Ski",
  "year": 1848,
  "reclat": 59.73333,
  "reclong": 10.86667
},
{
  "_id": {
    "$oid": "656a815c9fbd268c204f06a8"
  },
  "name": "Slavetic",
  "year": 1868,
  "reclat": 45.68333,
  "reclong": 15.6
},
{
  "_id": {
    "$oid": "656a815c9fbd268c204f06a9"
  },
  "name": "Slobodka",
  "year": 1818,
  "reclat": 55,
  "reclong": 35
},
{
  "_id": {
    "$oid": "656a815c9fbd268c204f06ab"
  },
  "name": "Soko-Banja",
  "year": 1877,
  "reclat": 43.66667,
  "reclong": 21.86667
},
{
  "_id": {
    "$oid": "656a815c9fbd268c204f06ac"
  },
  "name": "Sologne",
  "year": 1860,
  "reclat": 47.36667,
  "reclong": 1.73333
},
{
  "_id": {
    "$oid": "656a815c9fbd268c204f06ae"
  },
  "name": "Sone",
  "year": 1866,
  "reclat": 35.16667,
  "reclong": 135.33333
},
{
  "_id": {
    "$oid": "656a815c9fbd268c204f06b2"
  },
  "name": "St. Caprais-de-Quinsac",
  "year": 1883,
  "reclat": 44.75,
  "reclong": 0.05
},
{
  "_id": {
    "$oid": "656a815c9fbd268c204f06b3"
  },
  "name": "St. Christophe-la-Chartreuse",
  "year": 1841,
  "reclat": 46.95,
  "reclong": -1.5
},
{
  "_id": {
    "$oid": "656a815c9fbd268c204f06b4"
  },
  "name": "St. Denis Westrem",
  "year": 1855,
  "reclat": 51.05,
  "reclong": 3.75
},
{
  "_id": {
    "$oid": "656a815c9fbd268c204f06b5"
  },
  "name": "St. Germain-du-Pinel",
  "year": 1890,
  "reclat": 48.01667,
  "reclong": -1.15
},
{
  "_id": {
    "$oid": "656a815c9fbd268c204f06b9"
  },
  "name": "St. Mesmin",
  "year": 1866,
  "reclat": 48.45,
  "reclong": 3.93333
},
{
  "_id": {
    "$oid": "656a815c9fbd268c204f06bc"
  },
  "name": "Ställdalen",
  "year": 1876,
  "reclat": 59.93333,
  "reclong": 14.95
},
{
  "_id": {
    "$oid": "656a815c9fbd268c204f06bd"
  },
  "name": "Stannern",
  "year": 1808,
  "reclat": 49.28333,
  "reclong": 15.56667
},
{
  "_id": {
    "$oid": "656a815c9fbd268c204f06be"
  },
  "name": "Stavropol",
  "year": 1857,
  "reclat": 45.05,
  "reclong": 41.98333
},
{
  "_id": {
    "$oid": "656a815c9fbd268c204f06cc"
  },
  "name": "Supuhee",
  "year": 1865,
  "reclat": 26.71667,
  "reclong": 84.21667
},
{
  "_id": {
    "$oid": "656a815c9fbd268c204f06d0"
  },
  "name": "Tadjera",
  "year": 1867,
  "reclat": 36.18333,
  "reclong": 5.41667
},
{
  "_id": {
    "$oid": "656a815c9fbd268c204f06d3"
  },
  "name": "Takenouchi",
  "year": 1880,
  "reclat": 35.38333,
  "reclong": 134.9
},
{
  "_id": {
    "$oid": "656a815c9fbd268c204f06dd"
  },
  "name": "Tenham",
  "year": 1879,
  "reclat": -25.73333,
  "reclong": 142.95
},
{
  "_id": {
    "$oid": "656a815c9fbd268c204f06de"
  },
  "name": "Tennasilm",
  "year": 1872,
  "reclat": 58.03333,
  "reclong": 26.95
},
{
  "_id": {
    "$oid": "656a815c9fbd268c204f06e3"
  },
  "name": "Tieschitz",
  "year": 1878,
  "reclat": 49.6,
  "reclong": 17.11667
},
{
  "_id": {
    "$oid": "656a815c9fbd268c204f06e6"
  },
  "name": "Timochin",
  "year": 1807,
  "reclat": 54.5,
  "reclong": 35.2
},
{
  "_id": {
    "$oid": "656a815c9fbd268c204f06e9"
  },
  "name": "Tjabe",
  "year": 1869,
  "reclat": -7.08333,
  "reclong": 111.53333
},
{
  "_id": {
    "$oid": "656a815c9fbd268c204f06ec"
  },
  "name": "Tomatlan",
  "year": 1879,
  "reclat": 20.16667,
  "reclong": -105.21667
},
{
  "_id": {
    "$oid": "656a815c9fbd268c204f06f2"
  },
  "name": "Toulouse",
  "year": 1812,
  "reclat": 43.6,
  "reclong": 1.4
},
{
  "_id": {
    "$oid": "656a815c9fbd268c204f06f3"
  },
  "name": "Tounkin",
  "year": 1824,
  "reclat": 51.73333,
  "reclong": 102.53333
},
{
  "_id": {
    "$oid": "656a815c9fbd268c204f06f4"
  },
  "name": "Tourinnes-la-Grosse",
  "year": 1863,
  "reclat": 50.78333,
  "reclong": 4.76667
},
{
  "_id": {
    "$oid": "656a815c9fbd268c204f06f6"
  },
  "name": "Trenzano",
  "year": 1856,
  "reclat": 45.46667,
  "reclong": 10
},
{
  "_id": {
    "$oid": "656a815c9fbd268c204f0701"
  },
  "name": "Tysnes Island",
  "year": 1884,
  "reclat": 60,
  "reclong": 5.61667
},
{
  "_id": {
    "$oid": "656a815c9fbd268c204f0708"
  },
  "name": "Uden",
  "year": 1840,
  "reclat": 51.65,
  "reclong": 5.61667
},
{
  "_id": {
    "$oid": "656a815c9fbd268c204f0709"
  },
  "name": "Udipi",
  "year": 1866,
  "reclat": 13.48333,
  "reclong": 74.78333
},
{
  "_id": {
    "$oid": "656a815c9fbd268c204f070c"
  },
  "name": "Umbala",
  "year": 1822,
  "reclat": 30.33333,
  "reclong": 76.33333
},
{
  "_id": {
    "$oid": "656a815c9fbd268c204f0712"
  },
  "name": "Utrecht",
  "year": 1843,
  "reclat": 52.11667,
  "reclong": 5.18333
},
{
  "_id": {
    "$oid": "656a815c9fbd268c204f071a"
  },
  "name": "Vavilovka",
  "year": 1876,
  "reclat": 46.15,
  "reclong": 32.83333
},
{
  "_id": {
    "$oid": "656a815c9fbd268c204f071c"
  },
  "name": "Veramin",
  "year": 1880,
  "reclat": 35.33333,
  "reclong": 51.63333
},
{
  "_id": {
    "$oid": "656a815c9fbd268c204f071d"
  },
  "name": "Verkhne Tschirskaia",
  "year": 1843,
  "reclat": 48.41667,
  "reclong": 43.2
},
{
  "_id": {
    "$oid": "656a815c9fbd268c204f071e"
  },
  "name": "Vernon County",
  "year": 1865,
  "reclat": 43.5,
  "reclong": -91.16667
},
{
  "_id": {
    "$oid": "656a815c9fbd268c204f0724"
  },
  "name": "Virba",
  "year": 1873,
  "reclat": 43.53333,
  "reclong": 22.63333
},
{
  "_id": {
    "$oid": "656a815c9fbd268c204f0728"
  },
  "name": "Vouillé",
  "year": 1831,
  "reclat": 46.63333,
  "reclong": 0.16667
},
{
  "_id": {
    "$oid": "656a815c9fbd268c204f072a"
  },
  "name": "Warrenton",
  "year": 1877,
  "reclat": 38.68333,
  "reclong": -91.15
},
{
  "_id": {
    "$oid": "656a815c9fbd268c204f072d"
  },
  "name": "Wessely",
  "year": 1831,
  "reclat": 48.95,
  "reclong": 17.38333
},
{
  "_id": {
    "$oid": "656a815c9fbd268c204f072e"
  },
  "name": "Weston",
  "year": 1807,
  "reclat": 41.266667,
  "reclong": -73.266667
},
{
  "_id": {
    "$oid": "656a815c9fbd268c204f0735"
  },
  "name": "Wittekrantz",
  "year": 1880,
  "reclat": -32.5,
  "reclong": 23
},
{
  "_id": {
    "$oid": "656a815c9fbd268c204f0743"
  },
  "name": "Yatoor",
  "year": 1852,
  "reclat": 14.3,
  "reclong": 79.76667
},
{
  "_id": {
    "$oid": "656a815c9fbd268c204f0744"
  },
  "name": "Yonozu",
  "year": 1837,
  "reclat": 37.75,
  "reclong": 139
},
{
  "_id": {
    "$oid": "656a815c9fbd268c204f0745"
  },
  "name": "Yorktown (New York)",
  "year": 1869,
  "reclat": 41.28333,
  "reclong": -73.81667
},
{
  "_id": {
    "$oid": "656a815c9fbd268c204f0749"
  },
  "name": "Zaborzika",
  "year": 1818,
  "reclat": 50.28333,
  "reclong": 27.68333
},
{
  "_id": {
    "$oid": "656a815c9fbd268c204f074a"
  },
  "name": "Zabrodje",
  "year": 1893,
  "reclat": 55.18333,
  "reclong": 27.91667
},
{
  "_id": {
    "$oid": "656a815c9fbd268c204f074e"
  },
  "name": "Zaisho",
  "year": 1898,
  "reclat": 33.7,
  "reclong": 133.8
},
{
  "_id": {
    "$oid": "656a815c9fbd268c204f0751"
  },
  "name": "Zavid",
  "year": 1897,
  "reclat": 44.4,
  "reclong": 19.11667
},
{
  "_id": {
    "$oid": "656a815c9fbd268c204f0752"
  },
  "name": "Zebrak",
  "year": 1824,
  "reclat": 49.88333,
  "reclong": 13.91667
},
{
  "_id": {
    "$oid": "656a815c9fbd268c204f0757"
  },
  "name": "Zmenj",
  "year": 1858,
  "reclat": 51.83333,
  "reclong": 26.83333
},
{
  "_id": {
    "$oid": "656a815c9fbd268c204f0758"
  },
  "name": "Zomba",
  "year": 1899,
  "reclat": -15.18333,
  "reclong": 35.28333
},
{
  "_id": {
    "$oid": "656a815c9fbd268c204f0759"
  },
  "name": "Zsadany",
  "year": 1875,
  "reclat": 46.93333,
  "reclong": 21.5
},
{
  "_id": {
    "$oid": "656a815c9fbd268c204f075f"
  },
  "name": "Abo",
  "year": 1840,
  "reclat": 60.43333,
  "reclong": 22.3
},
{
  "_id": {
    "$oid": "656a815c9fbd268c204f08f4"
  },
  "name": "Adalia",
  "year": 1883,
  "reclat": 36.9,
  "reclong": 30.68333
},
{
  "_id": {
    "$oid": "656a815c9fbd268c204f08fa"
  },
  "name": "Admire",
  "year": 1881,
  "reclat": 38.7,
  "reclong": -96.1
},
{
  "_id": {
    "$oid": "656a815c9fbd268c204f095f"
  },
  "name": "Alexander County",
  "year": 1875,
  "reclat": 35.75,
  "reclong": -81.25
},
{
  "_id": {
    "$oid": "656a815c9fbd268c204f0963"
  },
  "name": "Algoma",
  "year": 1887,
  "reclat": 44.65,
  "reclong": -87.46667
},
{
  "_id": {
    "$oid": "656a815d9fbd268c204f1057"
  },
  "name": "Alt Bela",
  "year": 1898,
  "reclat": 49.76667,
  "reclong": 18.25
},
{
  "_id": {
    "$oid": "656a815d9fbd268c204f105c"
  },
  "name": "Ameca-Ameca",
  "year": 1889,
  "reclat": 20.58333,
  "reclong": -104.06667
},
{
  "_id": {
    "$oid": "656a815d9fbd268c204f105e"
  },
  "name": "Andryushki",
  "year": 1898,
  "reclat": 49.65,
  "reclong": 29.63333
},
{
  "_id": {
    "$oid": "656a815d9fbd268c204f106d"
  },
  "name": "Apoala",
  "year": 1889,
  "reclat": 17.7,
  "reclong": -97
},
{
  "_id": {
    "$oid": "656a815d9fbd268c204f107e"
  },
  "name": "Arispe",
  "year": 1896,
  "reclat": 30.33333,
  "reclong": -109.98333
},
{
  "_id": {
    "$oid": "656a815d9fbd268c204f1080"
  },
  "name": "Arlington",
  "year": 1894,
  "reclat": 44.6,
  "reclong": -94.1
},
{
  "_id": {
    "$oid": "656a815d9fbd268c204f1083"
  },
  "name": "Armanty",
  "year": 1898,
  "reclat": 47,
  "reclong": 88
},
{
  "_id": {
    "$oid": "656a815d9fbd268c204f108b"
  },
  "name": "Asheville",
  "year": 1839,
  "reclat": 35.58333,
  "reclong": -82.53333
},
{
  "_id": {
    "$oid": "656a815d9fbd268c204f1094"
  },
  "name": "Assam",
  "year": 1846,
  "reclat": 26,
  "reclong": 92
},
{
  "_id": {
    "$oid": "656a815d9fbd268c204f1690"
  },
  "name": "Auburn",
  "year": 1867,
  "reclat": 32.63333,
  "reclong": -85.5
},
{
  "_id": {
    "$oid": "656a815d9fbd268c204f1691"
  },
  "name": "Augusta County",
  "year": 1858,
  "reclat": 38.16667,
  "reclong": -79.08333
},
{
  "_id": {
    "$oid": "656a815d9fbd268c204f1692"
  },
  "name": "Augustinovka",
  "year": 1890,
  "reclat": 48.06667,
  "reclong": 35.08333
},
{
  "_id": {
    "$oid": "656a815d9fbd268c204f1699"
  },
  "name": "Babb's Mill (Blake's Iron)",
  "year": 1876,
  "reclat": 36.3,
  "reclong": -82.88333
},
{
  "_id": {
    "$oid": "656a815d9fbd268c204f169a"
  },
  "name": "Babb's Mill (Troost's Iron)",
  "year": 1842,
  "reclat": 36.3,
  "reclong": -82.88333
},
{
  "_id": {
    "$oid": "656a815d9fbd268c204f169c"
  },
  "name": "Bacubirito",
  "year": 1863,
  "reclat": 26.2,
  "reclong": -107.83333
},
{
  "_id": {
    "$oid": "656a815d9fbd268c204f16a0"
  },
  "name": "Bald Eagle",
  "year": 1891,
  "reclat": 41.28333,
  "reclong": -77.05
},
{
  "_id": {
    "$oid": "656a815d9fbd268c204f16a2"
  },
  "name": "Ballarat",
  "year": 1867,
  "reclat": -37.57083,
  "reclong": 143.82533
},
{
  "_id": {
    "$oid": "656a815d9fbd268c204f16a4"
  },
  "name": "Ballinoo",
  "year": 1892,
  "reclat": -27.7,
  "reclong": 115.76667
},
{
  "_id": {
    "$oid": "656a815d9fbd268c204f16ab"
  },
  "name": "Barranca Blanca",
  "year": 1855,
  "reclat": -28.08333,
  "reclong": -69.33333
},
{
  "_id": {
    "$oid": "656a815d9fbd268c204f16ac"
  },
  "name": "Barratta",
  "year": 1845,
  "reclat": -35.3,
  "reclong": 144.56667
},
{
  "_id": {
    "$oid": "656a815d9fbd268c204f16c6"
  },
  "name": "Bear Creek",
  "year": 1866,
  "reclat": 39.6,
  "reclong": -105.3
},
{
  "_id": {
    "$oid": "656a815d9fbd268c204f16d6"
  },
  "name": "Bella Roca",
  "year": 1888,
  "reclat": 24.9,
  "reclong": -105.4
},
{
  "_id": {
    "$oid": "656a815d9fbd268c204f16e0"
  },
  "name": "Bendock",
  "year": 1898,
  "reclat": -37.15,
  "reclong": 148.91667
},
{
  "_id": {
    "$oid": "656a815d9fbd268c204f16e8"
  },
  "name": "Berdyansk",
  "year": 1843,
  "reclat": 46.75,
  "reclong": 36.81667
},
{
  "_id": {
    "$oid": "656a815d9fbd268c204f16f8"
  },
  "name": "Bingera",
  "year": 1880,
  "reclat": -29.88333,
  "reclong": 150.56667
},
{
  "_id": {
    "$oid": "656a815d9fbd268c204f1707"
  },
  "name": "Bischtübe",
  "year": 1888,
  "reclat": 51.95,
  "reclong": 62.2
},
{
  "_id": {
    "$oid": "656a815d9fbd268c204f170a"
  },
  "name": "Bitburg",
  "year": 1805,
  "reclat": 49.96667,
  "reclong": 6.53333
},
{
  "_id": {
    "$oid": "656a815d9fbd268c204f170b"
  },
  "name": "Black Mountain",
  "year": 1839,
  "reclat": 35.58333,
  "reclong": -82.35
},
{
  "_id": {
    "$oid": "656a815d9fbd268c204f1715"
  },
  "name": "Blue Tier",
  "year": 1890,
  "reclat": -41.18333,
  "reclong": 148.03333
},
{
  "_id": {
    "$oid": "656a815d9fbd268c204f172a"
  },
  "name": "Bluff (a)",
  "year": 1878,
  "reclat": 29.87861,
  "reclong": -96.87222
},
{
  "_id": {
    "$oid": "656a815d9fbd268c204f1732"
  },
  "name": "Bohumilitz",
  "year": 1829,
  "reclat": 49.05,
  "reclong": 13.76667
},
{
  "_id": {
    "$oid": "656a815d9fbd268c204f1735"
  },
  "name": "Bond Springs",
  "year": 1898,
  "reclat": -23.5,
  "reclong": 133.83333
},
{
  "_id": {
    "$oid": "656a815d9fbd268c204f173a"
  },
  "name": "Boogaldi",
  "year": 1900,
  "reclat": -31.15,
  "reclong": 149.11667
},
{
  "_id": {
    "$oid": "656a815d9fbd268c204f173e"
  },
  "name": "Botetourt County",
  "year": 1850,
  "reclat": 37.5,
  "reclong": -79.75
},
{
  "_id": {
    "$oid": "656a815d9fbd268c204f1752"
  },
  "name": "Brahin",
  "year": 1810,
  "reclat": 52.5,
  "reclong": 30.33333
},
{
  "_id": {
    "$oid": "656a815d9fbd268c204f1755"
  },
  "name": "Brenham",
  "year": 1882,
  "reclat": 37.5825,
  "reclong": -99.16361
},
{
  "_id": {
    "$oid": "656a815d9fbd268c204f1757"
  },
  "name": "Bridgewater",
  "year": 1890,
  "reclat": 35.71667,
  "reclong": -81.86667
},
{
  "_id": {
    "$oid": "656a815d9fbd268c204f1797"
  },
  "name": "Burlington",
  "year": 1819,
  "reclat": 42.75,
  "reclong": -75.18333
},
{
  "_id": {
    "$oid": "656a815d9fbd268c204f179f"
  },
  "name": "Butler",
  "year": 1874,
  "reclat": 38.3,
  "reclong": -94.36667
},
{
  "_id": {
    "$oid": "656a815d9fbd268c204f17a0"
  },
  "name": "Cacaria",
  "year": 1867,
  "reclat": 24.5,
  "reclong": -104.8
},
{
  "_id": {
    "$oid": "656a815d9fbd268c204f17a2"
  },
  "name": "Cachiyuyal",
  "year": 1874,
  "reclat": -25,
  "reclong": -69.5
},
{
  "_id": {
    "$oid": "656a815d9fbd268c204f17be"
  },
  "name": "Cambria",
  "year": 1818,
  "reclat": 43.2,
  "reclong": -78.8
},
{
  "_id": {
    "$oid": "656a815d9fbd268c204f17f8"
  },
  "name": "Campo de Pucara (iron)",
  "year": 1879,
  "reclat": -27.66667,
  "reclong": -67.11667
},
{
  "_id": {
    "$oid": "656a815d9fbd268c204f17fa"
  },
  "name": "Canton",
  "year": 1894,
  "reclat": 34.2,
  "reclong": -84.48333
},
{
  "_id": {
    "$oid": "656a815d9fbd268c204f17fd"
  },
  "name": "Canyon City",
  "year": 1875,
  "reclat": 40.9,
  "reclong": -123.1
},
{
  "_id": {
    "$oid": "656a815d9fbd268c204f17fe"
  },
  "name": "Canyon Diablo",
  "year": 1891,
  "reclat": 35.05,
  "reclong": -111.03333
},
{
  "_id": {
    "$oid": "656a815d9fbd268c204f1801"
  },
  "name": "Cape York",
  "year": 1818,
  "reclat": 76.13333,
  "reclong": -64.93333
},
{
  "_id": {
    "$oid": "656a815d9fbd268c204f1802"
  },
  "name": "Caperr",
  "year": 1869,
  "reclat": -45.28333,
  "reclong": -70.48333
},
{
  "_id": {
    "$oid": "656a815d9fbd268c204f1805"
  },
  "name": "Carcote",
  "year": 1888,
  "reclat": -24,
  "reclong": -69
},
{
  "_id": {
    "$oid": "656a815d9fbd268c204f180e"
  },
  "name": "Carlton",
  "year": 1887,
  "reclat": 31.91667,
  "reclong": -98.03333
},
{
  "_id": {
    "$oid": "656a815d9fbd268c204f1812"
  },
  "name": "Carthage",
  "year": 1840,
  "reclat": 36.26667,
  "reclong": -85.98333
},
{
  "_id": {
    "$oid": "656a815d9fbd268c204f1815"
  },
  "name": "Casas Grandes",
  "year": 1867,
  "reclat": 30.4,
  "reclong": -107.8
},
{
  "_id": {
    "$oid": "656a815d9fbd268c204f1816"
  },
  "name": "Casey County",
  "year": 1877,
  "reclat": 37.25,
  "reclong": -85
},
{
  "_id": {
    "$oid": "656a815d9fbd268c204f181b"
  },
  "name": "Castray River",
  "year": 1899,
  "reclat": -41.5,
  "reclong": 145.41667
},
{
  "_id": {
    "$oid": "656a815d9fbd268c204f1842"
  },
  "name": "Cedar (Texas)",
  "year": 1900,
  "reclat": 29.82806,
  "reclong": -96.90861
},
{
  "_id": {
    "$oid": "656a815d9fbd268c204f1843"
  },
  "name": "Cedartown",
  "year": 1898,
  "reclat": 34.01667,
  "reclong": -85.26667
},
{
  "_id": {
    "$oid": "656a815d9fbd268c204f184a"
  },
  "name": "Chañaral",
  "year": 1884,
  "reclat": -26.5,
  "reclong": -70.25
},
{
  "_id": {
    "$oid": "656a815d9fbd268c204f184e"
  },
  "name": "Charcas",
  "year": 1804,
  "reclat": 23.08333,
  "reclong": -101.01667
},
{
  "_id": {
    "$oid": "656a815d9fbd268c204f1852"
  },
  "name": "Chesterville",
  "year": 1849,
  "reclat": 34.7,
  "reclong": -81.2
},
{
  "_id": {
    "$oid": "656a815d9fbd268c204f1858"
  },
  "name": "Chilkoot",
  "year": 1881,
  "reclat": 59.33333,
  "reclong": -136
},
{
  "_id": {
    "$oid": "656a815d9fbd268c204f185f"
  },
  "name": "Chulafinnee",
  "year": 1873,
  "reclat": 33.5,
  "reclong": -85.66667
},
{
  "_id": {
    "$oid": "656a815d9fbd268c204f1860"
  },
  "name": "Chupaderos",
  "year": 1852,
  "reclat": 27,
  "reclong": -105.1
},
{
  "_id": {
    "$oid": "656a815d9fbd268c204f1862"
  },
  "name": "Cincinnati",
  "year": 1870,
  "reclat": 39.11667,
  "reclong": -84.5
},
{
  "_id": {
    "$oid": "656a815d9fbd268c204f186d"
  },
  "name": "Cleveland",
  "year": 1860,
  "reclat": 34.88333,
  "reclong": -84.78333
},
{
  "_id": {
    "$oid": "656a815d9fbd268c204f1874"
  },
  "name": "Coahuila",
  "year": 1837,
  "reclat": 28.7,
  "reclong": -102.73333
},
{
  "_id": {
    "$oid": "656a815d9fbd268c204f1875"
  },
  "name": "Cobija",
  "year": 1892,
  "reclat": -22.56667,
  "reclong": -70.25
},
{
  "_id": {
    "$oid": "656a815d9fbd268c204f1881"
  },
  "name": "Colfax",
  "year": 1880,
  "reclat": 35.3,
  "reclong": -81.73333
},
{
  "_id": {
    "$oid": "656a815d9fbd268c204f189e"
  },
  "name": "Coolac",
  "year": 1874,
  "reclat": -34.96667,
  "reclong": 148.125
},
{
  "_id": {
    "$oid": "656a815d9fbd268c204f18a4"
  },
  "name": "Coopertown",
  "year": 1860,
  "reclat": 36.43333,
  "reclong": -87
},
{
  "_id": {
    "$oid": "656a815d9fbd268c204f18a8"
  },
  "name": "Copiapo",
  "year": 1863,
  "reclat": -27.3,
  "reclong": -70.4
},
{
  "_id": {
    "$oid": "656a815d9fbd268c204f18ae"
  },
  "name": "Corrizatillo",
  "year": 1884,
  "reclat": -26.03333,
  "reclong": -70.33333
},
{
  "_id": {
    "$oid": "656a815d9fbd268c204f18b0"
  },
  "name": "Cosby's Creek",
  "year": 1837,
  "reclat": 35.78333,
  "reclong": -83.25
},
{
  "_id": {
    "$oid": "656a815d9fbd268c204f18b2"
  },
  "name": "Costilla Peak",
  "year": 1881,
  "reclat": 36.83333,
  "reclong": -105.23333
},
{
  "_id": {
    "$oid": "656a815d9fbd268c204f18b6"
  },
  "name": "Covert",
  "year": 1896,
  "reclat": 39.2,
  "reclong": -98.78333
},
{
  "_id": {
    "$oid": "656a815d9fbd268c204f18b8"
  },
  "name": "Cowra",
  "year": 1888,
  "reclat": -33.85,
  "reclong": 148.68333
},
{
  "_id": {
    "$oid": "656a815d9fbd268c204f18ef"
  },
  "name": "Crab Orchard",
  "year": 1887,
  "reclat": 35.83333,
  "reclong": -84.91667
},
{
  "_id": {
    "$oid": "656a815d9fbd268c204f18f0"
  },
  "name": "Cranberry Plains",
  "year": 1852,
  "reclat": 37.23333,
  "reclong": -80.73333
},
{
  "_id": {
    "$oid": "656a815d9fbd268c204f18f1"
  },
  "name": "Cranbourne",
  "year": 1854,
  "reclat": -38.1,
  "reclong": 145.3
},
{
  "_id": {
    "$oid": "656a815d9fbd268c204f18fc"
  },
  "name": "Cuba",
  "year": 1871,
  "reclat": 22,
  "reclong": -80
},
{
  "_id": {
    "$oid": "656a815d9fbd268c204f194f"
  },
  "name": "Dalton",
  "year": 1879,
  "reclat": 34.8,
  "reclong": -84.98333
},
{
  "_id": {
    "$oid": "656a815d9fbd268c204f1dac"
  },
  "name": "Dayton",
  "year": 1892,
  "reclat": 39.75,
  "reclong": -84.16667
},
{
  "_id": {
    "$oid": "656a815d9fbd268c204f1dbc"
  },
  "name": "Deep Springs",
  "year": 1846,
  "reclat": 36.5,
  "reclong": -79.75
},
{
  "_id": {
    "$oid": "656a815d9fbd268c204f1dbd"
  },
  "name": "Dehesa",
  "year": 1866,
  "reclat": -33.5,
  "reclong": -70.5
},
{
  "_id": {
    "$oid": "656a815d9fbd268c204f1dc1"
  },
  "name": "Dellys",
  "year": 1865,
  "reclat": 36.91667,
  "reclong": 3.91667
},
{
  "_id": {
    "$oid": "656a815d9fbd268c204f1dcc"
  },
  "name": "Densmore (1879)",
  "year": 1879,
  "reclat": 39.65,
  "reclong": -99.68333
},
{
  "_id": {
    "$oid": "656a815d9fbd268c204f1dcf"
  },
  "name": "Denton County",
  "year": 1856,
  "reclat": 33,
  "reclong": -97
},
{
  "_id": {
    "$oid": "656a815d9fbd268c204f1df2"
  },
  "name": "Dexter",
  "year": 1889,
  "reclat": 33.81667,
  "reclong": -97
},
{
  "_id": {
    "$oid": "656a815d9fbd268c204f26cf"
  },
  "name": "Doyleville",
  "year": 1887,
  "reclat": 38.41667,
  "reclong": -106.58333
},
{
  "_id": {
    "$oid": "656a815d9fbd268c204f26d7"
  },
  "name": "Duel Hill (1854)",
  "year": 1854,
  "reclat": 35.85,
  "reclong": -82.7
},
{
  "_id": {
    "$oid": "656a815d9fbd268c204f26d8"
  },
  "name": "Duel Hill (1873)",
  "year": 1873,
  "reclat": 35.85,
  "reclong": -82.7
},
{
  "_id": {
    "$oid": "656a815d9fbd268c204f26e5"
  },
  "name": "Eagle Station",
  "year": 1880,
  "reclat": 38.61667,
  "reclong": -84.96667
},
{
  "_id": {
    "$oid": "656a815d9fbd268c204f2705"
  },
  "name": "El Capitan",
  "year": 1893,
  "reclat": 33.5,
  "reclong": -105.5
},
{
  "_id": {
    "$oid": "656a815e9fbd268c204f306f"
  },
  "name": "Eli Elwah",
  "year": 1888,
  "reclat": -34.5,
  "reclong": 144.71667
},
{
  "_id": {
    "$oid": "656a815e9fbd268c204f3083"
  },
  "name": "Emmitsburg",
  "year": 1854,
  "reclat": 39.71667,
  "reclong": -77.3
},
{
  "_id": {
    "$oid": "656a815e9fbd268c204f3087"
  },
  "name": "Enon",
  "year": 1883,
  "reclat": 39.86667,
  "reclong": -83.95
},
{
  "_id": {
    "$oid": "656a815e9fbd268c204f3091"
  },
  "name": "Estacado",
  "year": 1883,
  "reclat": 33.9,
  "reclong": -101.75
},
{
  "_id": {
    "$oid": "656a815e9fbd268c204f30e8"
  },
  "name": "Forsyth County",
  "year": 1891,
  "reclat": 36.1,
  "reclong": -80.2
},
{
  "_id": {
    "$oid": "656a815e9fbd268c204f30e9"
  },
  "name": "Fort Pierre",
  "year": 1856,
  "reclat": 44.35,
  "reclong": -100.38333
},
{
  "_id": {
    "$oid": "656a815e9fbd268c204f30f0"
  },
  "name": "Franceville",
  "year": 1890,
  "reclat": 38.81667,
  "reclong": -104.61667
},
{
  "_id": {
    "$oid": "656a815e9fbd268c204f30f3"
  },
  "name": "Frankfort (iron)",
  "year": 1866,
  "reclat": 38.2,
  "reclong": -84.83333
},
{
  "_id": {
    "$oid": "656a815e9fbd268c204f30f5"
  },
  "name": "Franklinville",
  "year": 1888,
  "reclat": 38.5,
  "reclong": -100
},
{
  "_id": {
    "$oid": "656a815e9fbd268c204f340b"
  },
  "name": "Fukue",
  "year": 1849,
  "reclat": 32.7,
  "reclong": 128.85
},
{
  "_id": {
    "$oid": "656a815e9fbd268c204f3443"
  },
  "name": "Gerona",
  "year": 1899,
  "reclat": 41.96667,
  "reclong": 2.81667
},
{
  "_id": {
    "$oid": "656a815e9fbd268c204f3449"
  },
  "name": "Gibeon",
  "year": 1836,
  "reclat": -25.5,
  "reclong": 18
},
{
  "_id": {
    "$oid": "656a815e9fbd268c204f344c"
  },
  "name": "Gilgoin",
  "year": 1889,
  "reclat": -30.38333,
  "reclong": 147.2
},
{
  "_id": {
    "$oid": "656a815e9fbd268c204f3456"
  },
  "name": "Glorieta Mountain",
  "year": 1884,
  "reclat": 35.6,
  "reclong": -105.8
},
{
  "_id": {
    "$oid": "656a815e9fbd268c204f3458"
  },
  "name": "Goalpara",
  "year": 1868,
  "reclat": 26.16667,
  "reclong": 90.6
},
{
  "_id": {
    "$oid": "656a815e9fbd268c204f346a"
  },
  "name": "Grand Rapids",
  "year": 1883,
  "reclat": 42.96667,
  "reclong": -85.76667
},
{
  "_id": {
    "$oid": "656a815e9fbd268c204f35e4"
  },
  "name": "Greenbrier County",
  "year": 1880,
  "reclat": 37.83333,
  "reclong": -80.31667
},
{
  "_id": {
    "$oid": "656a815e9fbd268c204f414b"
  },
  "name": "Guilford County",
  "year": 1822,
  "reclat": 35.56667,
  "reclong": -79.83333
},
{
  "_id": {
    "$oid": "656a815e9fbd268c204f4161"
  },
  "name": "Hainholz",
  "year": 1856,
  "reclat": 52.28333,
  "reclong": 8.91667
},
{
  "_id": {
    "$oid": "656a815e9fbd268c204f42c5"
  },
  "name": "Hammond",
  "year": 1884,
  "reclat": 44.91667,
  "reclong": -92.43333
},
{
  "_id": {
    "$oid": "656a815e9fbd268c204f42c9"
  },
  "name": "Haniet-el-Beguel",
  "year": 1888,
  "reclat": 32.48333,
  "reclong": 4.4
},
{
  "_id": {
    "$oid": "656a815e9fbd268c204f42f7"
  },
  "name": "Hayden Creek",
  "year": 1895,
  "reclat": 45,
  "reclong": -114
},
{
  "_id": {
    "$oid": "656a815e9fbd268c204f4304"
  },
  "name": "Hex River Mountains",
  "year": 1882,
  "reclat": -33.31667,
  "reclong": 19.61667
},
{
  "_id": {
    "$oid": "656a815e9fbd268c204f4308"
  },
  "name": "Hildreth",
  "year": 1894,
  "reclat": 40.33333,
  "reclong": -99.03333
},
{
  "_id": {
    "$oid": "656a815e9fbd268c204f430f"
  },
  "name": "Holland's Store",
  "year": 1887,
  "reclat": 34.36667,
  "reclong": -85.43333
},
{
  "_id": {
    "$oid": "656a815e9fbd268c204f4317"
  },
  "name": "Hopper",
  "year": 1889,
  "reclat": 36.55,
  "reclong": -79.78333
},
{
  "_id": {
    "$oid": "656a815e9fbd268c204f437d"
  },
  "name": "Ilimaes (iron)",
  "year": 1870,
  "reclat": -26,
  "reclong": -70
},
{
  "_id": {
    "$oid": "656a815e9fbd268c204f4380"
  },
  "name": "Illinois Gulch",
  "year": 1899,
  "reclat": 46.68333,
  "reclong": -112.55
},
{
  "_id": {
    "$oid": "656a815e9fbd268c204f4381"
  },
  "name": "Imilac",
  "year": 1822,
  "reclat": -24.20333,
  "reclong": -68.80667
},
{
  "_id": {
    "$oid": "656a815e9fbd268c204f4385"
  },
  "name": "Indian Valley",
  "year": 1887,
  "reclat": 36.93333,
  "reclong": -80.5
},
{
  "_id": {
    "$oid": "656a815e9fbd268c204f4388"
  },
  "name": "Indio Rico",
  "year": 1887,
  "reclat": -38.33333,
  "reclong": -60.88333
},
{
  "_id": {
    "$oid": "656a815e9fbd268c204f438f"
  },
  "name": "Iquique",
  "year": 1871,
  "reclat": -20.18333,
  "reclong": -69.73333
},
{
  "_id": {
    "$oid": "656a815e9fbd268c204f4390"
  },
  "name": "Iredell",
  "year": 1898,
  "reclat": 31.96667,
  "reclong": -97.86667
},
{
  "_id": {
    "$oid": "656a815e9fbd268c204f4391"
  },
  "name": "Iron Creek",
  "year": 1869,
  "reclat": 53,
  "reclong": -112
},
{
  "_id": {
    "$oid": "656a815e9fbd268c204f4392"
  },
  "name": "Iron River",
  "year": 1889,
  "reclat": 46.07944,
  "reclong": -88.55972
},
{
  "_id": {
    "$oid": "656a815e9fbd268c204f43a1"
  },
  "name": "Ivanpah",
  "year": 1880,
  "reclat": 35.33333,
  "reclong": -115.31667
},
{
  "_id": {
    "$oid": "656a815e9fbd268c204f43a3"
  },
  "name": "Jackson County",
  "year": 1846,
  "reclat": 36.41667,
  "reclong": -85.5
},
{
  "_id": {
    "$oid": "656a815e9fbd268c204f43a5"
  },
  "name": "Jamestown",
  "year": 1885,
  "reclat": 46.61667,
  "reclong": -98.5
},
{
  "_id": {
    "$oid": "656a815e9fbd268c204f43ad"
  },
  "name": "Jenny's Creek",
  "year": 1883,
  "reclat": 37.9,
  "reclong": -82.38333
},
{
  "_id": {
    "$oid": "656a815e9fbd268c204f43b0"
  },
  "name": "Jerome (Kansas)",
  "year": 1894,
  "reclat": 38.76667,
  "reclong": -100.73333
},
{
  "_id": {
    "$oid": "656a815e9fbd268c204f43b2"
  },
  "name": "Jiapigou",
  "year": 1880,
  "reclat": 42.83333,
  "reclong": 127.5
},
{
  "_id": {
    "$oid": "656a815e9fbd268c204f4675"
  },
  "name": "Joe Wright Mountain",
  "year": 1884,
  "reclat": 35.76667,
  "reclong": -91.5
},
{
  "_id": {
    "$oid": "656a815e9fbd268c204f4676"
  },
  "name": "Joel's Iron",
  "year": 1858,
  "reclat": -24,
  "reclong": -69
},
{
  "_id": {
    "$oid": "656a815e9fbd268c204f468f"
  },
  "name": "Jonesboro",
  "year": 1891,
  "reclat": 36.3,
  "reclong": -82.46667
},
{
  "_id": {
    "$oid": "656a815e9fbd268c204f4694"
  },
  "name": "Juncal",
  "year": 1866,
  "reclat": -26,
  "reclong": -69.25
},
{
  "_id": {
    "$oid": "656a815e9fbd268c204f46b6"
  },
  "name": "Karagai",
  "year": 1900,
  "reclat": 51.11667,
  "reclong": 57.91667
},
{
  "_id": {
    "$oid": "656a815e9fbd268c204f46bc"
  },
  "name": "Kaufman",
  "year": 1893,
  "reclat": 32.58333,
  "reclong": -96.41667
},
{
  "_id": {
    "$oid": "656a815e9fbd268c204f46c0"
  },
  "name": "Kendall County",
  "year": 1887,
  "reclat": 29.4,
  "reclong": -98.5
},
{
  "_id": {
    "$oid": "656a815e9fbd268c204f46c3"
  },
  "name": "Kenton County",
  "year": 1889,
  "reclat": 38.81667,
  "reclong": -84.6
},
{
  "_id": {
    "$oid": "656a815e9fbd268c204f46d3"
  },
  "name": "Kingston",
  "year": 1891,
  "reclat": 32.9,
  "reclong": -107.73333
},
{
  "_id": {
    "$oid": "656a815e9fbd268c204f46d7"
  },
  "name": "Kissij",
  "year": 1899,
  "reclat": 54.86667,
  "reclong": 50.88333
},
{
  "_id": {
    "$oid": "656a815e9fbd268c204f46dd"
  },
  "name": "Kodaikanal",
  "year": 1898,
  "reclat": 10.26667,
  "reclong": 77.4
},
{
  "_id": {
    "$oid": "656a815e9fbd268c204f46de"
  },
  "name": "Kofa",
  "year": 1893,
  "reclat": 33.5,
  "reclong": -114
},
{
  "_id": {
    "$oid": "656a815e9fbd268c204f46df"
  },
  "name": "Kokomo",
  "year": 1862,
  "reclat": 40.48333,
  "reclong": -86.36667
},
{
  "_id": {
    "$oid": "656a815e9fbd268c204f46e0"
  },
  "name": "Kokstad",
  "year": 1884,
  "reclat": -30.55,
  "reclong": 29.41667
},
{
  "_id": {
    "$oid": "656a815e9fbd268c204f4701"
  },
  "name": "Kulnine",
  "year": 1886,
  "reclat": -34.15,
  "reclong": 141.78333
},
{
  "_id": {
    "$oid": "656a815e9fbd268c204f470d"
  },
  "name": "La Caille",
  "year": 1828,
  "reclat": 43.73333,
  "reclong": 6.78333
},
{
  "_id": {
    "$oid": "656a815e9fbd268c204f4711"
  },
  "name": "La Grange",
  "year": 1860,
  "reclat": 38.4,
  "reclong": -85.36667
},
{
  "_id": {
    "$oid": "656a815e9fbd268c204f4714"
  },
  "name": "La Porte",
  "year": 1900,
  "reclat": 41.6,
  "reclong": -86.71667
},
{
  "_id": {
    "$oid": "656a815e9fbd268c204f4715"
  },
  "name": "La Primitiva",
  "year": 1888,
  "reclat": -19.91667,
  "reclong": -69.81667
},
{
  "_id": {
    "$oid": "656a815f9fbd268c204f5012"
  },
  "name": "Laurens County",
  "year": 1857,
  "reclat": 34.5,
  "reclong": -82.03333
},
{
  "_id": {
    "$oid": "656a815f9fbd268c204f501f"
  },
  "name": "Lenarto",
  "year": 1814,
  "reclat": 49,
  "reclong": 21
},
{
  "_id": {
    "$oid": "656a815f9fbd268c204f5784"
  },
  "name": "Lexington County",
  "year": 1880,
  "reclat": 34,
  "reclong": -81.25
},
{
  "_id": {
    "$oid": "656a815f9fbd268c204f5786"
  },
  "name": "Lick Creek",
  "year": 1879,
  "reclat": 35.66667,
  "reclong": -80.25
},
{
  "_id": {
    "$oid": "656a815f9fbd268c204f5789"
  },
  "name": "Lime Creek",
  "year": 1834,
  "reclat": 31.55,
  "reclong": -87.51667
},
{
  "_id": {
    "$oid": "656a815f9fbd268c204f578b"
  },
  "name": "Linville",
  "year": 1882,
  "reclat": 35.86667,
  "reclong": -81.91667
},
{
  "_id": {
    "$oid": "656a815f9fbd268c204f579b"
  },
  "name": "Locust Grove",
  "year": 1857,
  "reclat": 33.33333,
  "reclong": -84.1
},
{
  "_id": {
    "$oid": "656a815f9fbd268c204f579e"
  },
  "name": "Lonaconing",
  "year": 1888,
  "reclat": 39.41667,
  "reclong": -79.15
},
{
  "_id": {
    "$oid": "656a815f9fbd268c204f57ac"
  },
  "name": "Long Island",
  "year": 1891,
  "reclat": 39.93333,
  "reclong": -99.6
},
{
  "_id": {
    "$oid": "656a815f9fbd268c204f57b8"
  },
  "name": "Loreto",
  "year": 1896,
  "reclat": 26.01667,
  "reclong": -111.36667
},
{
  "_id": {
    "$oid": "656a815f9fbd268c204f57bc"
  },
  "name": "Los Reyes",
  "year": 1897,
  "reclat": 19.26667,
  "reclong": -97.28333
},
{
  "_id": {
    "$oid": "656a815f9fbd268c204f57db"
  },
  "name": "Losttown",
  "year": 1868,
  "reclat": 34.25,
  "reclong": -84.5
},
{
  "_id": {
    "$oid": "656a815f9fbd268c204f5820"
  },
  "name": "Lucky Hill",
  "year": 1885,
  "reclat": 17.9,
  "reclong": -77.63333
},
{
  "_id": {
    "$oid": "656a815f9fbd268c204f5822"
  },
  "name": "Luis Lopez",
  "year": 1896,
  "reclat": 34,
  "reclong": -106.96667
},
{
  "_id": {
    "$oid": "656a815f9fbd268c204f5823"
  },
  "name": "Lujan",
  "year": 1878,
  "reclat": -34.66667,
  "reclong": -59.36667
},
{
  "_id": {
    "$oid": "656a815f9fbd268c204f5828"
  },
  "name": "Lutschaunig's Stone",
  "year": 1861,
  "reclat": -27,
  "reclong": -70
},
{
  "_id": {
    "$oid": "656a815f9fbd268c204f5c62"
  },
  "name": "Madoc",
  "year": 1854,
  "reclat": 44.5,
  "reclong": -77.46667
},
{
  "_id": {
    "$oid": "656a815f9fbd268c204f5c64"
  },
  "name": "Magura",
  "year": 1840,
  "reclat": 49.33333,
  "reclong": 19.48333
},
{
  "_id": {
    "$oid": "656a815f9fbd268c204f5c65"
  },
  "name": "Mainz",
  "year": 1852,
  "reclat": 50,
  "reclong": 8.26667
},
{
  "_id": {
    "$oid": "656a815f9fbd268c204f5c6b"
  },
  "name": "Makarewa",
  "year": 1879,
  "reclat": -46.31667,
  "reclong": 168.4
},
{
  "_id": {
    "$oid": "656a815f9fbd268c204f5c73"
  },
  "name": "Mantos Blancos",
  "year": 1876,
  "reclat": -23.45,
  "reclong": -70.11667
},
{
  "_id": {
    "$oid": "656a815f9fbd268c204f5c81"
  },
  "name": "Marshall County",
  "year": 1860,
  "reclat": 37,
  "reclong": -88.25
},
{
  "_id": {
    "$oid": "656a815f9fbd268c204f5c83"
  },
  "name": "Mart",
  "year": 1898,
  "reclat": 31.5,
  "reclong": -96.88333
},
{
  "_id": {
    "$oid": "656a815f9fbd268c204f5c93"
  },
  "name": "McKinney",
  "year": 1870,
  "reclat": 33.18333,
  "reclong": -96.71667
},
{
  "_id": {
    "$oid": "656a815f9fbd268c204f5c97"
  },
  "name": "Mejillones",
  "year": 1875,
  "reclat": -23.1,
  "reclong": -70.5
},
{
  "_id": {
    "$oid": "656a815f9fbd268c204f5ca4"
  },
  "name": "Merceditas",
  "year": 1884,
  "reclat": -26.33333,
  "reclong": -70.28333
},
{
  "_id": {
    "$oid": "656a815f9fbd268c204f6927"
  },
  "name": "Minas Gerais",
  "year": 1888,
  "reclat": -18.5,
  "reclong": -44
},
{
  "_id": {
    "$oid": "656a815f9fbd268c204f6929"
  },
  "name": "Mincy",
  "year": 1857,
  "reclat": 36.55,
  "reclong": -93.1
},
{
  "_id": {
    "$oid": "656a815f9fbd268c204f692e"
  },
  "name": "Misteca",
  "year": 1804,
  "reclat": 16.8,
  "reclong": -97.1
},
{
  "_id": {
    "$oid": "656a815f9fbd268c204f6931"
  },
  "name": "Moctezuma",
  "year": 1889,
  "reclat": 29.8,
  "reclong": -109.66667
},
{
  "_id": {
    "$oid": "656a815f9fbd268c204f693c"
  },
  "name": "Moonbi",
  "year": 1892,
  "reclat": -30.91667,
  "reclong": 151.28333
},
{
  "_id": {
    "$oid": "656a815f9fbd268c204f6943"
  },
  "name": "Morland",
  "year": 1890,
  "reclat": 39.33333,
  "reclong": -100.06667
},
{
  "_id": {
    "$oid": "656a815f9fbd268c204f6945"
  },
  "name": "Morradal",
  "year": 1892,
  "reclat": 62,
  "reclong": 7.66667
},
{
  "_id": {
    "$oid": "656a815f9fbd268c204f6947"
  },
  "name": "Morristown",
  "year": 1887,
  "reclat": 36.2,
  "reclong": -83.38333
},
{
  "_id": {
    "$oid": "656a815f9fbd268c204f6965"
  },
  "name": "Mount Joy",
  "year": 1887,
  "reclat": 39.78333,
  "reclong": -77.21667
},
{
  "_id": {
    "$oid": "656a815f9fbd268c204f696a"
  },
  "name": "Mount Morris (New York)",
  "year": 1897,
  "reclat": 42.7,
  "reclong": -77.88333
},
{
  "_id": {
    "$oid": "656a815f9fbd268c204f696c"
  },
  "name": "Mount Ouray",
  "year": 1898,
  "reclat": 38.41667,
  "reclong": -106.21667
},
{
  "_id": {
    "$oid": "656a815f9fbd268c204f6991"
  },
  "name": "Mount Vernon",
  "year": 1868,
  "reclat": 36.93333,
  "reclong": -87.4
},
{
  "_id": {
    "$oid": "656a815f9fbd268c204f69b5"
  },
  "name": "Mühlau",
  "year": 1877,
  "reclat": 47.28333,
  "reclong": 11.41667
},
{
  "_id": {
    "$oid": "656a815f9fbd268c204f69b6"
  },
  "name": "Muizenberg",
  "year": 1880,
  "reclat": -34.1,
  "reclong": 18.46667
},
{
  "_id": {
    "$oid": "656a815f9fbd268c204f69d2"
  },
  "name": "Mungindi",
  "year": 1897,
  "reclat": -28.93333,
  "reclong": 148.95
},
{
  "_id": {
    "$oid": "656a815f9fbd268c204f69d5"
  },
  "name": "Murfreesboro",
  "year": 1847,
  "reclat": 35.83333,
  "reclong": -86.41667
},
{
  "_id": {
    "$oid": "656a815f9fbd268c204f69d9"
  },
  "name": "Murphy",
  "year": 1899,
  "reclat": 35.1,
  "reclong": -84.03333
},
{
  "_id": {
    "$oid": "656a815f9fbd268c204f69df"
  },
  "name": "Nagy-Vázsony",
  "year": 1890,
  "reclat": 46.98333,
  "reclong": 17.7
},
{
  "_id": {
    "$oid": "656a815f9fbd268c204f69ea"
  },
  "name": "Narraburra",
  "year": 1855,
  "reclat": -34.25,
  "reclong": 147.7
},
{
  "_id": {
    "$oid": "656a815f9fbd268c204f69fd"
  },
  "name": "Nelson County",
  "year": 1856,
  "reclat": 37.75,
  "reclong": -85.5
},
{
  "_id": {
    "$oid": "656a815f9fbd268c204f69fe"
  },
  "name": "Nenntmannsdorf",
  "year": 1872,
  "reclat": 50.96667,
  "reclong": 13.95
},
{
  "_id": {
    "$oid": "656a815f9fbd268c204f6a00"
  },
  "name": "Ness County (1894)",
  "year": 1894,
  "reclat": 38.5,
  "reclong": -99.6
},
{
  "_id": {
    "$oid": "656a815f9fbd268c204f6a03"
  },
  "name": "Netschaëvo",
  "year": 1846,
  "reclat": 54.23333,
  "reclong": 35.15
},
{
  "_id": {
    "$oid": "656a815f9fbd268c204f6a11"
  },
  "name": "Niagara",
  "year": 1879,
  "reclat": 48,
  "reclong": -97.93333
},
{
  "_id": {
    "$oid": "656a815f9fbd268c204f6a17"
  },
  "name": "Nochtuisk",
  "year": 1876,
  "reclat": 59.98333,
  "reclong": 117.58333
},
{
  "_id": {
    "$oid": "656a815f9fbd268c204f6a18"
  },
  "name": "Nocoleche",
  "year": 1895,
  "reclat": -29.86667,
  "reclong": 144.21667
},
{
  "_id": {
    "$oid": "656a815f9fbd268c204f6a1e"
  },
  "name": "Norin-Shibir",
  "year": 1900,
  "reclat": 51.85,
  "reclong": 107.91667
},
{
  "_id": {
    "$oid": "656a815f9fbd268c204f6a21"
  },
  "name": "North Chile",
  "year": 1875,
  "reclat": -23,
  "reclong": -69
},
{
  "_id": {
    "$oid": "656a81609fbd268c204f7bf0"
  },
  "name": "Oakley (stone)",
  "year": 1895,
  "reclat": 38.95,
  "reclong": -101.01667
},
{
  "_id": {
    "$oid": "656a81609fbd268c204f7bf3"
  },
  "name": "Obernkirchen",
  "year": 1863,
  "reclat": 52.26667,
  "reclong": 9.1
},
{
  "_id": {
    "$oid": "656a81609fbd268c204f7bf6"
  },
  "name": "Oczeretna",
  "year": 1871,
  "reclat": 49.31667,
  "reclong": 31.51667
},
{
  "_id": {
    "$oid": "656a81609fbd268c204f7c00"
  },
  "name": "Oktibbeha County",
  "year": 1854,
  "reclat": 33.5,
  "reclong": -89
},
{
  "_id": {
    "$oid": "656a81609fbd268c204f7c22"
  },
  "name": "Orange River (iron)",
  "year": 1855,
  "reclat": -30,
  "reclong": 25
},
{
  "_id": {
    "$oid": "656a81609fbd268c204f7c26"
  },
  "name": "Oroville",
  "year": 1893,
  "reclat": 39.68333,
  "reclong": -121.63333
},
{
  "_id": {
    "$oid": "656a81609fbd268c204f7c27"
  },
  "name": "Oscuro Mountains",
  "year": 1895,
  "reclat": 33.63333,
  "reclong": -106.38333
},
{
  "_id": {
    "$oid": "656a81609fbd268c204f7c9b"
  },
  "name": "Pampa del Infierno",
  "year": 1895,
  "reclat": -26.68333,
  "reclong": -61.08333
},
{
  "_id": {
    "$oid": "656a81609fbd268c204f7c9d"
  },
  "name": "Pan de Azucar",
  "year": 1887,
  "reclat": -26.5,
  "reclong": -69.5
},
{
  "_id": {
    "$oid": "656a81609fbd268c204f7d6b"
  },
  "name": "Pavlodar (pallasite)",
  "year": 1885,
  "reclat": 51.16667,
  "reclong": 77.33333
},
{
  "_id": {
    "$oid": "656a81609fbd268c204f7ff7"
  },
  "name": "Persimmon Creek",
  "year": 1893,
  "reclat": 35.05,
  "reclong": -84.23333
},
{
  "_id": {
    "$oid": "656a81609fbd268c204f7ff9"
  },
  "name": "Petropavlovsk",
  "year": 1841,
  "reclat": 53.35,
  "reclong": 87.18333
},
{
  "_id": {
    "$oid": "656a81609fbd268c204f7ffa"
  },
  "name": "Pevensey",
  "year": 1868,
  "reclat": -34.78333,
  "reclong": 144.66667
},
{
  "_id": {
    "$oid": "656a81609fbd268c204f800b"
  },
  "name": "Pipe Creek",
  "year": 1887,
  "reclat": 29.68333,
  "reclong": -98.91667
},
{
  "_id": {
    "$oid": "656a81609fbd268c204f800c"
  },
  "name": "Pirapora",
  "year": 1888,
  "reclat": -17.3,
  "reclong": -45
},
{
  "_id": {
    "$oid": "656a81609fbd268c204f800e"
  },
  "name": "Pittsburg",
  "year": 1850,
  "reclat": 40.43333,
  "reclong": -80
},
{
  "_id": {
    "$oid": "656a81609fbd268c204f801f"
  },
  "name": "Plymouth",
  "year": 1893,
  "reclat": 41.33333,
  "reclong": -86.31667
},
{
  "_id": {
    "$oid": "656a81609fbd268c204f8037"
  },
  "name": "Prairie Dog Creek",
  "year": 1893,
  "reclat": 39.63333,
  "reclong": -100.5
},
{
  "_id": {
    "$oid": "656a81609fbd268c204f8043"
  },
  "name": "Puquios",
  "year": 1885,
  "reclat": -27.15,
  "reclong": -69.91667
},
{
  "_id": {
    "$oid": "656a81609fbd268c204f8046"
  },
  "name": "Putnam County",
  "year": 1839,
  "reclat": 33.25,
  "reclong": -83.25
},
{
  "_id": {
    "$oid": "656a81619fbd268c204f8ddf"
  },
  "name": "Rafrüti",
  "year": 1886,
  "reclat": 47,
  "reclong": 7.83333
},
{
  "_id": {
    "$oid": "656a81619fbd268c204f8f06"
  },
  "name": "Rancho de la Pila (1882)",
  "year": 1882,
  "reclat": 24.11667,
  "reclong": -104.3
},
{
  "_id": {
    "$oid": "656a81619fbd268c204f8faa"
  },
  "name": "Red River",
  "year": 1808,
  "reclat": 32,
  "reclong": -95
},
{
  "_id": {
    "$oid": "656a81619fbd268c204f8fac"
  },
  "name": "Red Willow",
  "year": 1899,
  "reclat": 40.25,
  "reclong": -100.5
},
{
  "_id": {
    "$oid": "656a81619fbd268c204f8faf"
  },
  "name": "Reed City",
  "year": 1895,
  "reclat": 43.86667,
  "reclong": -85.51667
},
{
  "_id": {
    "$oid": "656a81619fbd268c204f8fd5"
  },
  "name": "Rhine Villa",
  "year": 1900,
  "reclat": -34.66667,
  "reclong": 139.28333
},
{
  "_id": {
    "$oid": "656a81619fbd268c204f90be"
  },
  "name": "Rodeo",
  "year": 1852,
  "reclat": 25.33333,
  "reclong": -104.66667
},
{
  "_id": {
    "$oid": "656a81619fbd268c204f90bf"
  },
  "name": "Roebourne",
  "year": 1892,
  "reclat": -22.33333,
  "reclong": 118
},
{
  "_id": {
    "$oid": "656a81619fbd268c204f913b"
  },
  "name": "Rosario",
  "year": 1896,
  "reclat": 14.6,
  "reclong": -88.68333
},
{
  "_id": {
    "$oid": "656a81619fbd268c204f9147"
  },
  "name": "Ruff's Mountain",
  "year": 1844,
  "reclat": 34.3,
  "reclong": -81.4
},
{
  "_id": {
    "$oid": "656a81619fbd268c204f914b"
  },
  "name": "Rushville",
  "year": 1866,
  "reclat": 39.61667,
  "reclong": -85.45
},
{
  "_id": {
    "$oid": "656a81619fbd268c204f914c"
  },
  "name": "Russel Gulch",
  "year": 1863,
  "reclat": 39.8,
  "reclong": -105.5
},
{
  "_id": {
    "$oid": "656a81619fbd268c204f914f"
  },
  "name": "Sacramento Mountains",
  "year": 1890,
  "reclat": 32.91667,
  "reclong": -104.66667
},
{
  "_id": {
    "$oid": "656a81619fbd268c204f9281"
  },
  "name": "Salt Lake City",
  "year": 1869,
  "reclat": 40.91667,
  "reclong": -111.66667
},
{
  "_id": {
    "$oid": "656a81619fbd268c204f9282"
  },
  "name": "Salt River",
  "year": 1850,
  "reclat": 37.95,
  "reclong": -85.78333
},
{
  "_id": {
    "$oid": "656a81619fbd268c204f9283"
  },
  "name": "Sam's Valley",
  "year": 1894,
  "reclat": 42.53333,
  "reclong": -122.875
},
{
  "_id": {
    "$oid": "656a81619fbd268c204f9284"
  },
  "name": "San Angelo",
  "year": 1897,
  "reclat": 31.41667,
  "reclong": -100.35
},
{
  "_id": {
    "$oid": "656a81619fbd268c204f9288"
  },
  "name": "San Cristobal",
  "year": 1882,
  "reclat": -23.43333,
  "reclong": -69.5
},
{
  "_id": {
    "$oid": "656a81619fbd268c204f9289"
  },
  "name": "San Emigdio",
  "year": 1887,
  "reclat": 36,
  "reclong": -119
},
{
  "_id": {
    "$oid": "656a81619fbd268c204f928a"
  },
  "name": "San Francisco del Mezquital",
  "year": 1868,
  "reclat": 23.48333,
  "reclong": -104.36667
},
{
  "_id": {
    "$oid": "656a81619fbd268c204f92d1"
  },
  "name": "San Pedro Springs",
  "year": 1887,
  "reclat": 29.5,
  "reclong": -98.5
},
{
  "_id": {
    "$oid": "656a81619fbd268c204f9315"
  },
  "name": "Santa Apolonia",
  "year": 1872,
  "reclat": 19.21667,
  "reclong": -98.3
},
{
  "_id": {
    "$oid": "656a81619fbd268c204f9316"
  },
  "name": "Santa Catharina",
  "year": 1875,
  "reclat": -26.21667,
  "reclong": -48.6
},
{
  "_id": {
    "$oid": "656a81619fbd268c204f9319"
  },
  "name": "Santa Rosa",
  "year": 1810,
  "reclat": 5.91667,
  "reclong": -73
},
{
  "_id": {
    "$oid": "656a81619fbd268c204f931e"
  },
  "name": "São Julião de Moreira",
  "year": 1883,
  "reclat": 41.76611,
  "reclong": -8.58361
},
{
  "_id": {
    "$oid": "656a81619fbd268c204f931f"
  },
  "name": "Saotome",
  "year": 1892,
  "reclat": 36.5,
  "reclong": 137
},
{
  "_id": {
    "$oid": "656a81619fbd268c204f9322"
  },
  "name": "Sarepta",
  "year": 1854,
  "reclat": 48.48333,
  "reclong": 44.81667
},
{
  "_id": {
    "$oid": "656a81619fbd268c204f950b"
  },
  "name": "Schwetz",
  "year": 1850,
  "reclat": 53.4,
  "reclong": 18.45
},
{
  "_id": {
    "$oid": "656a81619fbd268c204f952d"
  },
  "name": "Scottsville",
  "year": 1867,
  "reclat": 36.76667,
  "reclong": -86.16667
},
{
  "_id": {
    "$oid": "656a81619fbd268c204f9532"
  },
  "name": "Seeläsgen",
  "year": 1847,
  "reclat": 52.26667,
  "reclong": 15.55
},
{
  "_id": {
    "$oid": "656a81619fbd268c204f9538"
  },
  "name": "Selcany",
  "year": 1900,
  "reclat": 49.75,
  "reclong": 14.41667
},
{
  "_id": {
    "$oid": "656a81619fbd268c204f9546"
  },
  "name": "Seneca Falls",
  "year": 1850,
  "reclat": 42.91667,
  "reclong": -76.78333
},
{
  "_id": {
    "$oid": "656a81619fbd268c204f9548"
  },
  "name": "Serrania de Varas",
  "year": 1875,
  "reclat": -24.55,
  "reclong": -69.06667
},
{
  "_id": {
    "$oid": "656a81619fbd268c204f956e"
  },
  "name": "Shingle Springs",
  "year": 1869,
  "reclat": 38.66667,
  "reclong": -120.93333
},
{
  "_id": {
    "$oid": "656a81619fbd268c204f956f"
  },
  "name": "Shirahagi",
  "year": 1890,
  "reclat": 36.7,
  "reclong": 137.36667
},
{
  "_id": {
    "$oid": "656a81619fbd268c204f95f2"
  },
  "name": "Sierra Gorda",
  "year": 1898,
  "reclat": -22.9,
  "reclong": -69.35
},
{
  "_id": {
    "$oid": "656a81619fbd268c204f95f8"
  },
  "name": "Silver Crown",
  "year": 1887,
  "reclat": 41.23333,
  "reclong": -104.98333
},
{
  "_id": {
    "$oid": "656a81619fbd268c204f95fb"
  },
  "name": "Silverton (New South Wales)",
  "year": 1883,
  "reclat": -31.88333,
  "reclong": 141.2
},
{
  "_id": {
    "$oid": "656a81619fbd268c204f95fd"
  },
  "name": "Simbirsk (of P. Partsch)",
  "year": 1838,
  "reclat": 54.3,
  "reclong": 48.4
},
{
  "_id": {
    "$oid": "656a81619fbd268c204f9603"
  },
  "name": "Singhur",
  "year": 1847,
  "reclat": 18.31667,
  "reclong": 73.91667
},
{
  "_id": {
    "$oid": "656a81619fbd268c204f9626"
  },
  "name": "Slobodka (of P. Partsch)",
  "year": 1838,
  "reclat": 55,
  "reclong": 35
},
{
  "_id": {
    "$oid": "656a81619fbd268c204f962a"
  },
  "name": "Smithland",
  "year": 1839,
  "reclat": 37.13333,
  "reclong": -88.4
},
{
  "_id": {
    "$oid": "656a81619fbd268c204f962c"
  },
  "name": "Smith's Mountain",
  "year": 1863,
  "reclat": 36.41667,
  "reclong": -80
},
{
  "_id": {
    "$oid": "656a81619fbd268c204f962e"
  },
  "name": "Smithville",
  "year": 1840,
  "reclat": 35.98333,
  "reclong": -85.85
},
{
  "_id": {
    "$oid": "656a81619fbd268c204f963c"
  },
  "name": "South Bend",
  "year": 1893,
  "reclat": 41.65,
  "reclong": -86.21667
},
{
  "_id": {
    "$oid": "656a81619fbd268c204f964e"
  },
  "name": "Ssyromolotovo",
  "year": 1873,
  "reclat": 58.61667,
  "reclong": 98.93333
},
{
  "_id": {
    "$oid": "656a81619fbd268c204f9651"
  },
  "name": "St. Francois County",
  "year": 1863,
  "reclat": 37.75,
  "reclong": -90.5
},
{
  "_id": {
    "$oid": "656a81619fbd268c204f9652"
  },
  "name": "St. Genevieve County",
  "year": 1888,
  "reclat": 37.96667,
  "reclong": -90.31667
},
{
  "_id": {
    "$oid": "656a81619fbd268c204f9659"
  },
  "name": "Staunton",
  "year": 1869,
  "reclat": 38.21667,
  "reclong": -79.05
},
{
  "_id": {
    "$oid": "656a81619fbd268c204f965d"
  },
  "name": "Sterling",
  "year": 1900,
  "reclat": 40.6,
  "reclong": -103.18333
},
{
  "_id": {
    "$oid": "656a81619fbd268c204f9677"
  },
  "name": "Summit",
  "year": 1890,
  "reclat": 34.2,
  "reclong": -86.48333
},
{
  "_id": {
    "$oid": "656a81619fbd268c204f968d"
  },
  "name": "Surprise Springs",
  "year": 1899,
  "reclat": 34.16667,
  "reclong": -115.91667
},
{
  "_id": {
    "$oid": "656a81619fbd268c204f9699"
  },
  "name": "Tabarz",
  "year": 1854,
  "reclat": 50.88333,
  "reclong": 10.51667
},
{
  "_id": {
    "$oid": "656a81619fbd268c204f96ab"
  },
  "name": "Tamentit",
  "year": 1864,
  "reclat": 27.71667,
  "reclong": -0.25
},
{
  "_id": {
    "$oid": "656a81619fbd268c204f9705"
  },
  "name": "Tanokami Mountain",
  "year": 1885,
  "reclat": 34.91667,
  "reclong": 135.96667
},
{
  "_id": {
    "$oid": "656a81619fbd268c204f9715"
  },
  "name": "Tazewell",
  "year": 1853,
  "reclat": 36.43333,
  "reclong": -83.75
},
{
  "_id": {
    "$oid": "656a81619fbd268c204f971f"
  },
  "name": "Ternera",
  "year": 1891,
  "reclat": -27.33333,
  "reclong": -69.8
},
{
  "_id": {
    "$oid": "656a81619fbd268c204f9778"
  },
  "name": "Thomson",
  "year": 1888,
  "reclat": 33.46667,
  "reclong": -82.48333
},
{
  "_id": {
    "$oid": "656a81619fbd268c204f977e"
  },
  "name": "Thunda",
  "year": 1881,
  "reclat": -25.7,
  "reclong": 143.05
},
{
  "_id": {
    "$oid": "656a81619fbd268c204f977f"
  },
  "name": "Thurlow",
  "year": 1888,
  "reclat": 44.75,
  "reclong": -77.58333
},
{
  "_id": {
    "$oid": "656a81619fbd268c204f97ad"
  },
  "name": "Tombigbee River",
  "year": 1859,
  "reclat": 32.23333,
  "reclong": -88.2
},
{
  "_id": {
    "$oid": "656a81619fbd268c204f97ae"
  },
  "name": "Tomhannock Creek",
  "year": 1863,
  "reclat": 42.88333,
  "reclong": -73.6
},
{
  "_id": {
    "$oid": "656a81619fbd268c204f97af"
  },
  "name": "Tonganoxie",
  "year": 1886,
  "reclat": 39.08333,
  "reclong": -95.11667
},
{
  "_id": {
    "$oid": "656a81619fbd268c204f97b6"
  },
  "name": "Toubil River",
  "year": 1891,
  "reclat": 55.88333,
  "reclong": 89.1
},
{
  "_id": {
    "$oid": "656a81619fbd268c204f97ba"
  },
  "name": "Travis County (a)",
  "year": 1889,
  "reclat": 30.3,
  "reclong": -97.7
},
{
  "_id": {
    "$oid": "656a81619fbd268c204f97bb"
  },
  "name": "Travis County (b)",
  "year": 1889,
  "reclat": 30.55556,
  "reclong": -97.95278
},
{
  "_id": {
    "$oid": "656a81619fbd268c204f97bc"
  },
  "name": "Trenton",
  "year": 1858,
  "reclat": 43.36667,
  "reclong": -88.13333
},
{
  "_id": {
    "$oid": "656a81619fbd268c204f97c5"
  },
  "name": "Tucson",
  "year": 1850,
  "reclat": 31.85,
  "reclong": -110.96667
},
{
  "_id": {
    "$oid": "656a81619fbd268c204f9817"
  },
  "name": "Union County",
  "year": 1853,
  "reclat": 34.75,
  "reclong": -84
},
{
  "_id": {
    "$oid": "656a81619fbd268c204f9842"
  },
  "name": "Vaca Muerta",
  "year": 1861,
  "reclat": -25.75,
  "reclong": -70.5
},
{
  "_id": {
    "$oid": "656a81619fbd268c204f984f"
  },
  "name": "Verkhne Dnieprovsk",
  "year": 1876,
  "reclat": 48.63333,
  "reclong": 34.36667
},
{
  "_id": {
    "$oid": "656a81619fbd268c204f9850"
  },
  "name": "Verkhne Udinsk",
  "year": 1854,
  "reclat": 54.76667,
  "reclong": 113.98333
},
{
  "_id": {
    "$oid": "656a81619fbd268c204f9854"
  },
  "name": "Victoria West",
  "year": 1860,
  "reclat": -31.7,
  "reclong": 23.75
},
{
  "_id": {
    "$oid": "656a81619fbd268c204f985c"
  },
  "name": "Villedieu",
  "year": 1890,
  "reclat": 47.91667,
  "reclong": 4.35
},
{
  "_id": {
    "$oid": "656a81619fbd268c204f9862"
  },
  "name": "Wabar",
  "year": 1863,
  "reclat": 21.49972,
  "reclong": 50.47222
},
{
  "_id": {
    "$oid": "656a81619fbd268c204f9863"
  },
  "name": "Waconda",
  "year": 1873,
  "reclat": 39.33333,
  "reclong": -98.16667
},
{
  "_id": {
    "$oid": "656a81619fbd268c204f9867"
  },
  "name": "Wairarapa Valley",
  "year": 1863,
  "reclat": -41.31667,
  "reclong": 175.13333
},
{
  "_id": {
    "$oid": "656a81619fbd268c204f986b"
  },
  "name": "Waldron Ridge",
  "year": 1887,
  "reclat": 36.63333,
  "reclong": -83.83333
},
{
  "_id": {
    "$oid": "656a81619fbd268c204f986c"
  },
  "name": "Walker County",
  "year": 1832,
  "reclat": 34,
  "reclong": -87.16667
},
{
  "_id": {
    "$oid": "656a81619fbd268c204f988a"
  },
  "name": "Weaver Mountains",
  "year": 1898,
  "reclat": 34.25,
  "reclong": -112.75
},
{
  "_id": {
    "$oid": "656a81619fbd268c204f9893"
  },
  "name": "Welland",
  "year": 1888,
  "reclat": 43.01667,
  "reclong": -79.21667
},
{
  "_id": {
    "$oid": "656a81619fbd268c204f989f"
  },
  "name": "Western Arkansas",
  "year": 1890,
  "reclat": 35,
  "reclong": -94
},
{
  "_id": {
    "$oid": "656a81619fbd268c204f98a6"
  },
  "name": "Wichita County",
  "year": 1836,
  "reclat": 34.06667,
  "reclong": -98.91667
},
{
  "_id": {
    "$oid": "656a81619fbd268c204f98c5"
  },
  "name": "Winburg",
  "year": 1881,
  "reclat": -28.5,
  "reclong": 27
},
{
  "_id": {
    "$oid": "656a81619fbd268c204f98f5"
  },
  "name": "Wooster",
  "year": 1858,
  "reclat": 40.76667,
  "reclong": -81.95
},
{
  "_id": {
    "$oid": "656a81629fbd268c204fb562"
  },
  "name": "Yanhuitlan",
  "year": 1825,
  "reclat": 17.53333,
  "reclong": -97.35
},
{
  "_id": {
    "$oid": "656a81629fbd268c204fb563"
  },
  "name": "Yardea",
  "year": 1875,
  "reclat": -32.45,
  "reclong": 135.55
},
{
  "_id": {
    "$oid": "656a81629fbd268c204fb574"
  },
  "name": "York (iron)",
  "year": 1878,
  "reclat": 40.75,
  "reclong": -97.5
},
{
  "_id": {
    "$oid": "656a81629fbd268c204fb578"
  },
  "name": "Youndegin",
  "year": 1884,
  "reclat": -32.1,
  "reclong": 117.71667
}]